{"90600193": {"Native Name": "Aha Quin", "Native Violations": 1, "Non-Native Names": ["JACUMBA VALLEY RANCH WATER COMPANY", "99 PALMS INN AND SUITES", "LAIRD FAMILY ESTATE", "SAC VALLEY TRUCK STOP", "SHANT BHAVAN PUNJABI FUNERAL HOME", "PLAINVIEW MUTUAL WATER COMPANY", "GOOSELAKE WATER COMPANY", "RANCHO ESTATES MUTUAL WATER CO.", "STOCKTON BAPTIST CHURCH", "WINSHIP ELEMENTARY SCHOOL", "ROUND MOUNTAIN WATER COMPANY", "SIERRA EAST HOA", "OLD SUGAR MILL WINERY"], "Non-Native Violations": [1, 3, 3, 3, 4, 6, 8, 14, 17, 18, 21, 44, 76], "Rank": 13, "Total Rank": 14, "Percentile": 7.140000000000001, "Latitude": 33.628333, "Longitude": -114.61905, "PWSID": "90600193", "Embed": ["https://plotly.com/~amotiani22/86.embed", "https://plotly.com/~amotiani22/88.embed", "https://plotly.com/~amotiani22/65.embed", "https://plotly.com/~amotiani22/67.embed"], "Checks": 1.0}, "90600168": {"Native Name": null, "Native Violations": null, "Non-Native Names": null, "Non-Native Violations": null, "Rank": null, "Total Rank": null, "Percentile": null, "Latitude": null, "Longitude": null, "PWSID": "90600168", "Embed": [null, null, null, null], "Checks": null}, "90600601": {"Native Name": "Alturas Desert Rose Casino", "Native Violations": 0, "Non-Native Names": ["PASKENTA COMM. SERVICES DIST.", "THE COURTLAND GROUP", "MT. GEORGE ESTATES", "BOULEVARD PINES MOBILE HOME AND RV PARK"], "Non-Native Violations": [4, 7, 8, 9], "Rank": 5, "Total Rank": 5, "Percentile": 0.0, "Latitude": 41.439363, "Longitude": -120.58771, "PWSID": "90600601", "Embed": ["https://plotly.com/~amotiani22/92.embed", "https://plotly.com/~amotiani22/93.embed", "https://plotly.com/~amotiani22/77.embed", "https://plotly.com/~amotiani22/79.embed"], "Checks": 0.0}, "90400300": {"Native Name": "Arizona Village", "Native Violations": 161, "Non-Native Names": ["J.D. HEISKELL & CO.", "HUNGRY GULCH MWC", "CENTRAL VALLEY MEAT CO INC"], "Non-Native Violations": [14, 18, 35], "Rank": 1, "Total Rank": 4, "Percentile": 75.0, "Latitude": 34.818718, "Longitude": -114.62664, "PWSID": "90400300", "Embed": ["https://plotly.com/~amotiani22/56.embed", "https://plotly.com/~amotiani22/58.embed", "https://plotly.com/~amotiani22/60.embed", "https://plotly.com/~amotiani22/62.embed"], "Checks": 161.0}, "90605121": {"Native Name": "Arviso - Mobile Home Park", "Native Violations": 13, "Non-Native Names": ["DOGWOOD BLUE JAY CYN IMP", "SACRAMENTO SIKH SOCIETY", "SUPER DRIVE IN", "VACA VILLA APARTMENTS", "EDNA BEAMAN ELEMENTARY SCHOOL", "LAKE ELEMENTARY SCHOOL", "PESCADERO HIGH SCHOOL", "SACRAMENTO SOFTBALL COMPLEX (SWS)", "NEWELL COUNTY WATER DISTRICT", "APPLE VALLEY VIEW MWC", "BASS LAKE ANNEX 3", "NORTH FORK ELEMENTARY SCHOOL", "TWIN VALLEY INC", "FCSA #34/ MILLERTON NEW TOWN", "MD 24 TEAFORD MEADOW LAKES", "FAMILY TREE FARMS", "BAR-LEN MWC", "MILLSTREAM MOBILE HOME PARK", "LEMOORE, CITY OF", "LIZZE ENTERPRISES", "FINLEYS"], "Non-Native Violations": [1, 1, 1, 1, 2, 2, 2, 2, 3, 6, 9, 11, 11, 12, 13, 17, 19, 24, 25, 27, 30], "Rank": 7, "Total Rank": 22, "Percentile": 68.18, "Latitude": 33.311881, "Longitude": -116.96499, "PWSID": "90605121", "Embed": ["https://plotly.com/~amotiani22/101.embed", "https://plotly.com/~amotiani22/103.embed", "https://plotly.com/~amotiani22/83.embed", "https://plotly.com/~amotiani22/35.embed"], "Checks": 13.0}, "90605142": {"Native Name": "Augustine Casino", "Native Violations": 0, "Non-Native Names": ["JACUMBA VALLEY RANCH WATER COMPANY", "99 PALMS INN AND SUITES", "LAIRD FAMILY ESTATE", "SAC VALLEY TRUCK STOP", "SHANT BHAVAN PUNJABI FUNERAL HOME", "PLAINVIEW MUTUAL WATER COMPANY", "GOOSELAKE WATER COMPANY", "RANCHO ESTATES MUTUAL WATER CO.", "STOCKTON BAPTIST CHURCH", "WINSHIP ELEMENTARY SCHOOL", "ROUND MOUNTAIN WATER COMPANY", "SIERRA EAST HOA", "OLD SUGAR MILL WINERY"], "Non-Native Violations": [1, 3, 3, 3, 4, 6, 8, 14, 17, 18, 21, 44, 76], "Rank": 14, "Total Rank": 14, "Percentile": 0.0, "Latitude": 33.679872, "Longitude": -116.17656, "PWSID": "90605142", "Embed": ["https://plotly.com/~amotiani22/143.embed", "https://plotly.com/~amotiani22/144.embed", "https://plotly.com/~amotiani22/146.embed", "https://plotly.com/~amotiani22/148.embed"], "Checks": 0.0}, "90600119": {"Native Name": "Barona", "Native Violations": 1, "Non-Native Names": ["DOGWOOD BLUE JAY CYN IMP", "SACRAMENTO SIKH SOCIETY", "SUPER DRIVE IN", "VACA VILLA APARTMENTS", "EDNA BEAMAN ELEMENTARY SCHOOL", "LAKE ELEMENTARY SCHOOL", "PESCADERO HIGH SCHOOL", "SACRAMENTO SOFTBALL COMPLEX (SWS)", "NEWELL COUNTY WATER DISTRICT", "APPLE VALLEY VIEW MWC", "BASS LAKE ANNEX 3", "NORTH FORK ELEMENTARY SCHOOL", "TWIN VALLEY INC", "FCSA #34/ MILLERTON NEW TOWN", "MD 24 TEAFORD MEADOW LAKES", "FAMILY TREE FARMS", "BAR-LEN MWC", "MILLSTREAM MOBILE HOME PARK", "LEMOORE, CITY OF", "LIZZE ENTERPRISES", "FINLEYS"], "Non-Native Violations": [1, 1, 1, 1, 2, 2, 2, 2, 3, 6, 9, 11, 11, 12, 13, 17, 19, 24, 25, 27, 30], "Rank": 18, "Total Rank": 22, "Percentile": 18.180000000000007, "Latitude": 32.873849, "Longitude": -116.90477, "PWSID": "90600119", "Embed": ["https://plotly.com/~amotiani22/150.embed", "https://plotly.com/~amotiani22/152.embed", "https://plotly.com/~amotiani22/154.embed", "https://plotly.com/~amotiani22/156.embed"], "Checks": 1.0}, "90600118": {"Native Name": "Barona North", "Native Violations": 0, "Non-Native Names": ["DOGWOOD BLUE JAY CYN IMP", "SACRAMENTO SIKH SOCIETY", "SUPER DRIVE IN", "VACA VILLA APARTMENTS", "EDNA BEAMAN ELEMENTARY SCHOOL", "LAKE ELEMENTARY SCHOOL", "PESCADERO HIGH SCHOOL", "SACRAMENTO SOFTBALL COMPLEX (SWS)", "NEWELL COUNTY WATER DISTRICT", "APPLE VALLEY VIEW MWC", "BASS LAKE ANNEX 3", "NORTH FORK ELEMENTARY SCHOOL", "TWIN VALLEY INC", "FCSA #34/ MILLERTON NEW TOWN", "MD 24 TEAFORD MEADOW LAKES", "FAMILY TREE FARMS", "BAR-LEN MWC", "MILLSTREAM MOBILE HOME PARK", "LEMOORE, CITY OF", "LIZZE ENTERPRISES", "FINLEYS"], "Non-Native Violations": [1, 1, 1, 1, 2, 2, 2, 2, 3, 6, 9, 11, 11, 12, 13, 17, 19, 24, 25, 27, 30], "Rank": 22, "Total Rank": 22, "Percentile": 0.0, "Latitude": 32.883849, "Longitude": -116.90477, "PWSID": "90600118", "Embed": ["https://plotly.com/~amotiani22/157.embed", "https://plotly.com/~amotiani22/158.embed", "https://plotly.com/~amotiani22/160.embed", "https://plotly.com/~amotiani22/162.embed"], "Checks": 0.0}, "90605119": {"Native Name": "Bear River - Tish Non Village", "Native Violations": 2, "Non-Native Names": ["ALPHA OMEGA WINERY", "BIG SUR BAZAAR WS", "LEAPIN' LIZARD RV RANCH", "LOMA VISTA INN WS", "MESA  WATER DISTRICT", "ANCHORPOINT CHRISTIAN SCHOOL", "DEL ORO RIVER ISLAND SERV TERR #2", "BUTTE CITY COMMUNITY S.D.", "OASIS PROPERTY OWNERS ASSOCIATION", "BERRYESSA HIGHLANDS", "EAST OROSI CSD", "CANTUA CREEK VINEYARDS, IV, LLC.", "KNOLL ENTERPRISES"], "Non-Native Violations": [1, 1, 1, 2, 2, 3, 7, 8, 13, 22, 25, 26, 41], "Rank": 9, "Total Rank": 14, "Percentile": 35.709999999999994, "Latitude": 40.659753, "Longitude": -124.28153, "PWSID": "90605119", "Embed": ["https://plotly.com/~amotiani22/164.embed", "https://plotly.com/~amotiani22/166.embed", "https://plotly.com/~amotiani22/168.embed", "https://plotly.com/~amotiani22/170.embed"], "Checks": 2.0}, "90605125": {"Native Name": "Bear River/Singley Hill", "Native Violations": 3, "Non-Native Names": ["ALPHA OMEGA WINERY", "BIG SUR BAZAAR WS", "LEAPIN' LIZARD RV RANCH", "LOMA VISTA INN WS", "MESA  WATER DISTRICT", "ANCHORPOINT CHRISTIAN SCHOOL", "DEL ORO RIVER ISLAND SERV TERR #2", "BUTTE CITY COMMUNITY S.D.", "OASIS PROPERTY OWNERS ASSOCIATION", "BERRYESSA HIGHLANDS", "EAST OROSI CSD", "CANTUA CREEK VINEYARDS, IV, LLC.", "KNOLL ENTERPRISES"], "Non-Native Violations": [1, 1, 1, 2, 2, 3, 7, 8, 13, 22, 25, 26, 41], "Rank": 8, "Total Rank": 14, "Percentile": 42.86, "Latitude": 40.729753, "Longitude": -124.22153, "PWSID": "90605125", "Embed": ["https://plotly.com/~amotiani22/172.embed", "https://plotly.com/~amotiani22/174.embed", "https://plotly.com/~amotiani22/176.embed", "https://plotly.com/~amotiani22/178.embed"], "Checks": 3.0}, "90600159": {"Native Name": "Benton Paiute Tribe", "Native Violations": 78, "Non-Native Names": ["MOUNTAIN SPRINGS MUTUAL WATER COMPANY", "EAST VALLEY WATER DISTRICT", "CALISTOGA RANCH", "MOUNT WHITNEY GOLF CLUB", "GUATAY MUTUAL BENEFIT CORPORATION", "HURON, CITY OF"], "Non-Native Violations": [2, 3, 4, 11, 18, 26], "Rank": 1, "Total Rank": 7, "Percentile": 85.71000000000001, "Latitude": 37.583838, "Longitude": -118.23615, "PWSID": "90600159", "Embed": ["https://plotly.com/~amotiani22/39.embed", "https://plotly.com/~amotiani22/41.embed", "https://plotly.com/~amotiani22/43.embed", "https://plotly.com/~amotiani22/37.embed"], "Checks": 78.0}, "90600130": {"Native Name": "Bermuda Palms", "Native Violations": 3, "Non-Native Names": ["JACUMBA VALLEY RANCH WATER COMPANY", "99 PALMS INN AND SUITES", "LAIRD FAMILY ESTATE", "SAC VALLEY TRUCK STOP", "SHANT BHAVAN PUNJABI FUNERAL HOME", "PLAINVIEW MUTUAL WATER COMPANY", "GOOSELAKE WATER COMPANY", "RANCHO ESTATES MUTUAL WATER CO.", "STOCKTON BAPTIST CHURCH", "WINSHIP ELEMENTARY SCHOOL", "ROUND MOUNTAIN WATER COMPANY", "SIERRA EAST HOA", "OLD SUGAR MILL WINERY"], "Non-Native Violations": [1, 3, 3, 3, 4, 6, 8, 14, 17, 18, 21, 44, 76], "Rank": 10, "Total Rank": 14, "Percentile": 28.569999999999993, "Latitude": 33.715271, "Longitude": -116.235, "PWSID": "90600130", "Embed": ["https://plotly.com/~amotiani21/4.embed", "https://plotly.com/~amotiani21/6.embed", "https://plotly.com/~amotiani21/8.embed", "https://plotly.com/~amotiani21/10.embed"], "Checks": 3.0}, "90600120": {"Native Name": null, "Native Violations": null, "Non-Native Names": null, "Non-Native Violations": null, "Rank": null, "Total Rank": null, "Percentile": null, "Latitude": null, "Longitude": null, "PWSID": "90600120", "Embed": [null, null, null, null], "Checks": null}, "90600226": {"Native Name": "Big River Development", "Native Violations": 55, "Non-Native Names": ["J.D. HEISKELL & CO.", "HUNGRY GULCH MWC", "CENTRAL VALLEY MEAT CO INC"], "Non-Native Violations": [14, 18, 35], "Rank": 1, "Total Rank": 4, "Percentile": 75.0, "Latitude": 34.061931, "Longitude": -117.31995, "PWSID": "90600226", "Embed": [null, null, "https://plotly.com/~amotiani21/14.embed", "https://plotly.com/~amotiani21/16.embed"], "Checks": 55.0}, "90600121": {"Native Name": "Big Sandy Rancheria", "Native Violations": 77, "Non-Native Names": ["GOOSECROSS CELLARS", "KNIGHTS FERRY COMM. SVC. DIST.", "VIKING RV PARK", "NICASIO SCHOOL", "CAL FIRE-HIGH ROCK CONSERVATION CAMP"], "Non-Native Violations": [5, 6, 7, 9, 12], "Rank": 1, "Total Rank": 6, "Percentile": 83.33, "Latitude": 37.077273, "Longitude": -119.42982, "PWSID": "90600121", "Embed": [null, null, "https://plotly.com/~amotiani21/18.embed", "https://plotly.com/~amotiani21/20.embed"], "Checks": 77.0}, "90605152": {"Native Name": "Big Valley Community Center", "Native Violations": 0, "Non-Native Names": ["CAL FIRE - ISHI CONSERVATION CAMP", "7042 FOLSOM LLC WATER SYSTEM", "DIAMOND JACK'S RV RANCH", "SILVERFORK WATER ASSOCIATION", "ELKHORN REGIONAL PARK", "MATTOLE ELEMENTARY SCHOOL", "MELA'S MEXICAN RESTAURANT", "FANTESCA WINERY", "WINDY HILL WINERY", "YOSEMITE FORKS EST MUTUAL", "RIO BRAVO GREELEY SCHOOL WATER SYSTEM", "ALLENSWORTH CSD", "DUNNIGAN CHEVRON", "SHADY OAKS TRAILER RANCH", "ALPAUGH COMMUNITY SERVICES DISTRICT", "BARRY ELEMENTARY SCHOOL", "SAINT ANTHONY TRAILER PARK", "PANOCHE WATER DISTRICT"], "Non-Native Violations": [1, 2, 2, 2, 3, 3, 3, 6, 9, 9, 11, 12, 13, 14, 18, 20, 20, 22], "Rank": 19, "Total Rank": 19, "Percentile": 0.0, "Latitude": 39.05169799999999, "Longitude": -122.92071, "PWSID": "90605152", "Embed": [null, null, "https://plotly.com/~amotiani21/22.embed", "https://plotly.com/~amotiani21/24.embed"], "Checks": 0.0}, "90605164": {"Native Name": "Big Valley Rancheria Water District", "Native Violations": 1, "Non-Native Names": ["CAL FIRE - ISHI CONSERVATION CAMP", "7042 FOLSOM LLC WATER SYSTEM", "DIAMOND JACK'S RV RANCH", "SILVERFORK WATER ASSOCIATION", "ELKHORN REGIONAL PARK", "MATTOLE ELEMENTARY SCHOOL", "MELA'S MEXICAN RESTAURANT", "FANTESCA WINERY", "WINDY HILL WINERY", "YOSEMITE FORKS EST MUTUAL", "RIO BRAVO GREELEY SCHOOL WATER SYSTEM", "ALLENSWORTH CSD", "DUNNIGAN CHEVRON", "SHADY OAKS TRAILER RANCH", "ALPAUGH COMMUNITY SERVICES DISTRICT", "BARRY ELEMENTARY SCHOOL", "SAINT ANTHONY TRAILER PARK", "PANOCHE WATER DISTRICT"], "Non-Native Violations": [1, 2, 2, 2, 3, 3, 3, 6, 9, 9, 11, 12, 13, 14, 18, 20, 20, 22], "Rank": 18, "Total Rank": 19, "Percentile": 5.260000000000005, "Latitude": 39.061697999999986, "Longitude": -122.92071, "PWSID": "90605164", "Embed": ["https://plotly.com/~amotiani21/26.embed", "https://plotly.com/~amotiani21/28.embed", "https://plotly.com/~amotiani21/30.embed", "https://plotly.com/~amotiani21/35.embed"], "Checks": 1.0}, "90600122": {"Native Name": "Bishop Paiute-Shoshone Tribe", "Native Violations": 0, "Non-Native Names": ["MOUNTAIN SPRINGS MUTUAL WATER COMPANY", "EAST VALLEY WATER DISTRICT", "CALISTOGA RANCH", "MOUNT WHITNEY GOLF CLUB", "GUATAY MUTUAL BENEFIT CORPORATION", "HURON, CITY OF"], "Non-Native Violations": [2, 3, 4, 11, 18, 26], "Rank": 7, "Total Rank": 7, "Percentile": 0.0, "Latitude": 36.626033, "Longitude": -117.218616, "PWSID": "90600122", "Embed": ["https://plotly.com/~amotiani21/36.embed", "https://plotly.com/~amotiani21/37.embed", "https://plotly.com/~amotiani21/39.embed", "https://plotly.com/~amotiani21/41.embed"], "Checks": 0.0}, "90605117": {"Native Name": "Buena Vue Casino", "Native Violations": 0, "Non-Native Names": ["PRESTON WINERY", "ROARING CAMP", "GURNSEY AVENUE MUTUAL WATER SYSTEM", "KERN OIL AND REFINING CO.", "EB STONE", "OASIS GARDENS WATER CO.", "ELM COURT"], "Non-Native Violations": [1, 2, 4, 4, 11, 21, 24], "Rank": 8, "Total Rank": 8, "Percentile": 0.0, "Latitude": 38.346132, "Longitude": -120.94516, "PWSID": "90605117", "Embed": ["https://plotly.com/~amotiani21/42.embed", "https://plotly.com/~amotiani21/43.embed", "https://plotly.com/~amotiani21/45.embed", "https://plotly.com/~amotiani21/47.embed"], "Checks": 0.0}, "90605107": {"Native Name": "Cache Creek Casino Resort", "Native Violations": 2, "Non-Native Names": ["PRESTON WINERY", "ROARING CAMP", "GURNSEY AVENUE MUTUAL WATER SYSTEM", "KERN OIL AND REFINING CO.", "EB STONE", "OASIS GARDENS WATER CO.", "ELM COURT"], "Non-Native Violations": [1, 2, 4, 4, 11, 21, 24], "Rank": 6, "Total Rank": 8, "Percentile": 25.0, "Latitude": 38.857328, "Longitude": -122.21486, "PWSID": "90605107", "Embed": ["https://plotly.com/~amotiani21/49.embed", "https://plotly.com/~amotiani21/51.embed", "https://plotly.com/~amotiani21/53.embed", "https://plotly.com/~amotiani21/55.embed"], "Checks": 2.0}, "90600237": {"Native Name": "California Village", "Native Violations": 1, "Non-Native Names": ["NPS-WOLVERTON"], "Non-Native Violations": [45], "Rank": 2, "Total Rank": 2, "Percentile": 0.0, "Latitude": 34.85, "Longitude": -114.592, "PWSID": "90600237", "Embed": ["https://plotly.com/~amotiani21/57.embed", "https://plotly.com/~amotiani21/59.embed", "https://plotly.com/~amotiani21/61.embed", "https://plotly.com/~amotiani21/63.embed"], "Checks": 1.0}, "90605045": {"Native Name": "Campo Church Road System (HUD Homes)", "Native Violations": 0, "Non-Native Names": ["EDDO'S HARBOR & R V PARK", "NATIONAL CEMENT CO.-LEBEC PLANT", "FLORISTON WATER SYSTEM", "TRACT 92  CSD", "CEMEX - ALABAMA", "THE VILLAGE MOBILE HOME PARK"], "Non-Native Violations": [1, 3, 5, 5, 13, 15], "Rank": 7, "Total Rank": 7, "Percentile": 0.0, "Latitude": 32.664307, "Longitude": -116.46513, "PWSID": "90605045", "Embed": ["https://plotly.com/~amotiani21/64.embed", "https://plotly.com/~amotiani21/65.embed", "https://plotly.com/~amotiani21/67.embed", "https://plotly.com/~amotiani21/69.embed"], "Checks": 0.0}, "90600125": {"Native Name": "Chemehuevi Water", "Native Violations": 0, "Non-Native Names": ["J.D. HEISKELL & CO.", "HUNGRY GULCH MWC", "CENTRAL VALLEY MEAT CO INC"], "Non-Native Violations": [14, 18, 35], "Rank": 4, "Total Rank": 4, "Percentile": 0.0, "Latitude": 34.808718, "Longitude": -114.62664, "PWSID": "90600125", "Embed": ["https://plotly.com/~amotiani21/70.embed", "https://plotly.com/~amotiani21/71.embed", "https://plotly.com/~amotiani21/73.embed", "https://plotly.com/~amotiani21/75.embed"], "Checks": 0.0}, "90600247": {"Native Name": "Chukchansi Crossing", "Native Violations": 1, "Non-Native Names": ["GOOSECROSS CELLARS", "KNIGHTS FERRY COMM. SVC. DIST.", "VIKING RV PARK", "NICASIO SCHOOL", "CAL FIRE-HIGH ROCK CONSERVATION CAMP"], "Non-Native Violations": [5, 6, 7, 9, 12], "Rank": 6, "Total Rank": 6, "Percentile": 0.0, "Latitude": 37.206505, "Longitude": -119.6407, "PWSID": "90600247", "Embed": ["https://plotly.com/~amotiani21/77.embed", "https://plotly.com/~amotiani21/79.embed", "https://plotly.com/~amotiani21/81.embed", "https://plotly.com/~amotiani21/83.embed"], "Checks": 1.0}, "90605163": {"Native Name": "Chukchansi Gold Resort", "Native Violations": 0, "Non-Native Names": ["GOOSECROSS CELLARS", "KNIGHTS FERRY COMM. SVC. DIST.", "VIKING RV PARK", "NICASIO SCHOOL", "CAL FIRE-HIGH ROCK CONSERVATION CAMP"], "Non-Native Violations": [5, 6, 7, 9, 12], "Rank": 6, "Total Rank": 6, "Percentile": 0.0, "Latitude": 37.306505, "Longitude": -119.7207, "PWSID": "90605163", "Embed": ["https://plotly.com/~amotiani21/84.embed", "https://plotly.com/~amotiani21/85.embed", "https://plotly.com/~amotiani21/87.embed", "https://plotly.com/~amotiani21/89.embed"], "Checks": 0.0}, "90600126": {"Native Name": "Cold Springs Main", "Native Violations": 1, "Non-Native Names": ["GOOSECROSS CELLARS", "KNIGHTS FERRY COMM. SVC. DIST.", "VIKING RV PARK", "NICASIO SCHOOL", "CAL FIRE-HIGH ROCK CONSERVATION CAMP"], "Non-Native Violations": [5, 6, 7, 9, 12], "Rank": 6, "Total Rank": 6, "Percentile": 0.0, "Latitude": 36.981035, "Longitude": -119.38254, "PWSID": "90600126", "Embed": ["https://plotly.com/~amotiani21/91.embed", "https://plotly.com/~amotiani21/93.embed", "https://plotly.com/~amotiani21/95.embed", "https://plotly.com/~amotiani21/97.embed"], "Checks": 1.0}, "90605077": {"Native Name": "Cold Springs Subdivision", "Native Violations": 6, "Non-Native Names": ["GOOSECROSS CELLARS", "KNIGHTS FERRY COMM. SVC. DIST.", "VIKING RV PARK", "NICASIO SCHOOL", "CAL FIRE-HIGH ROCK CONSERVATION CAMP"], "Non-Native Violations": [5, 6, 7, 9, 12], "Rank": 4, "Total Rank": 6, "Percentile": 33.33, "Latitude": 36.991, "Longitude": -119.38254, "PWSID": "90605077", "Embed": ["https://plotly.com/~amotiani21/99.embed", "https://plotly.com/~amotiani21/101.embed", "https://plotly.com/~amotiani21/103.embed", "https://plotly.com/~amotiani21/105.embed"], "Checks": 6.0}, "90605046": {"Native Name": "Colusa Northern System", "Native Violations": 0, "Non-Native Names": ["DARWIN COMMUNITY SERVICE DISTRICT", "CAZADERO WATER COMPANY, INC. (PUC)", "SIERRA NORTH COMMUNITY SERVICE DISTRICT"], "Non-Native Violations": [2, 14, 18], "Rank": 4, "Total Rank": 4, "Percentile": 0.0, "Latitude": 39.254875, "Longitude": -122.04572, "PWSID": "90605046", "Embed": ["https://plotly.com/~amotiani21/106.embed", "https://plotly.com/~amotiani21/107.embed", "https://plotly.com/~amotiani21/109.embed", "https://plotly.com/~amotiani21/111.embed"], "Checks": 0.0}, "90605047": {"Native Name": "Colusa Southern System", "Native Violations": 0, "Non-Native Names": ["DARWIN COMMUNITY SERVICE DISTRICT", "CAZADERO WATER COMPANY, INC. (PUC)", "SIERRA NORTH COMMUNITY SERVICE DISTRICT"], "Non-Native Violations": [2, 14, 18], "Rank": 4, "Total Rank": 4, "Percentile": 0.0, "Latitude": 39.264874999999996, "Longitude": -122.04572, "PWSID": "90605047", "Embed": ["https://plotly.com/~amotiani21/112.embed", "https://plotly.com/~amotiani21/113.embed", "https://plotly.com/~amotiani21/115.embed", "https://plotly.com/~amotiani21/117.embed"], "Checks": 0.0}, "90600127": {"Native Name": "Dry Creek Rancheria", "Native Violations": 13, "Non-Native Names": ["CAL FIRE - ISHI CONSERVATION CAMP", "7042 FOLSOM LLC WATER SYSTEM", "DIAMOND JACK'S RV RANCH", "SILVERFORK WATER ASSOCIATION", "ELKHORN REGIONAL PARK", "MATTOLE ELEMENTARY SCHOOL", "MELA'S MEXICAN RESTAURANT", "FANTESCA WINERY", "WINDY HILL WINERY", "YOSEMITE FORKS EST MUTUAL", "RIO BRAVO GREELEY SCHOOL WATER SYSTEM", "ALLENSWORTH CSD", "DUNNIGAN CHEVRON", "SHADY OAKS TRAILER RANCH", "ALPAUGH COMMUNITY SERVICES DISTRICT", "BARRY ELEMENTARY SCHOOL", "SAINT ANTHONY TRAILER PARK", "PANOCHE WATER DISTRICT"], "Non-Native Violations": [1, 2, 2, 2, 3, 3, 3, 6, 9, 9, 11, 12, 13, 14, 18, 20, 20, 22], "Rank": 6, "Total Rank": 19, "Percentile": 68.42, "Latitude": 38.710228, "Longitude": -122.95704, "PWSID": "90600127", "Embed": ["https://plotly.com/~amotiani21/119.embed", "https://plotly.com/~amotiani21/121.embed", "https://plotly.com/~amotiani21/123.embed", "https://plotly.com/~amotiani21/125.embed"], "Checks": 13.0}, "90600128": {"Native Name": "Fort Bidwell Reservation", "Native Violations": 2, "Non-Native Names": ["PASKENTA COMM. SERVICES DIST.", "THE COURTLAND GROUP", "MT. GEORGE ESTATES", "BOULEVARD PINES MOBILE HOME AND RV PARK"], "Non-Native Violations": [4, 7, 8, 9], "Rank": 5, "Total Rank": 5, "Percentile": 0.0, "Latitude": 41.90749, "Longitude": -120.14789, "PWSID": "90600128", "Embed": ["https://plotly.com/~amotiani21/127.embed", "https://plotly.com/~amotiani21/129.embed", "https://plotly.com/~amotiani21/131.embed", "https://plotly.com/~amotiani21/133.embed"], "Checks": 2.0}, "90600129": {"Native Name": "Fort Independence", "Native Violations": 43, "Non-Native Names": ["MOUNTAIN SPRINGS MUTUAL WATER COMPANY", "EAST VALLEY WATER DISTRICT", "CALISTOGA RANCH", "MOUNT WHITNEY GOLF CLUB", "GUATAY MUTUAL BENEFIT CORPORATION", "HURON, CITY OF"], "Non-Native Violations": [2, 3, 4, 11, 18, 26], "Rank": 1, "Total Rank": 7, "Percentile": 85.71000000000001, "Latitude": 36.851729, "Longitude": -118.20743, "PWSID": "90600129", "Embed": ["https://plotly.com/~amotiani21/135.embed", "https://plotly.com/~amotiani21/137.embed", "https://plotly.com/~amotiani21/139.embed", "https://plotly.com/~amotiani21/141.embed"], "Checks": 43.0}, "90605174": {"Native Name": "Graton Resort and Casino", "Native Violations": 0, "Non-Native Names": ["LOS MOLINOS COMM. SERVICES DIST."], "Non-Native Violations": [14], "Rank": 2, "Total Rank": 2, "Percentile": 0.0, "Latitude": 38.347174, "Longitude": -122.69537, "PWSID": "90605174", "Embed": ["https://plotly.com/~amotiani21/142.embed", "https://plotly.com/~amotiani21/143.embed", "https://plotly.com/~amotiani21/145.embed", "https://plotly.com/~amotiani21/147.embed"], "Checks": 0.0}, "90605004": {"Native Name": "Grindstone Rancheria", "Native Violations": 313, "Non-Native Names": ["DARWIN COMMUNITY SERVICE DISTRICT", "CAZADERO WATER COMPANY, INC. (PUC)", "SIERRA NORTH COMMUNITY SERVICE DISTRICT"], "Non-Native Violations": [2, 14, 18], "Rank": 1, "Total Rank": 4, "Percentile": 75.0, "Latitude": 39.535446, "Longitude": -122.57667, "PWSID": "90605004", "Embed": ["https://plotly.com/~amotiani21/149.embed", "https://plotly.com/~amotiani21/151.embed", "https://plotly.com/~amotiani21/153.embed", "https://plotly.com/~amotiani21/155.embed"], "Checks": 313.0}, "90605172": {"Native Name": "Hard Rock Fire Mountain Water System", "Native Violations": 0, "Non-Native Names": ["PRESTON WINERY", "ROARING CAMP", "GURNSEY AVENUE MUTUAL WATER SYSTEM", "KERN OIL AND REFINING CO.", "EB STONE", "OASIS GARDENS WATER CO.", "ELM COURT"], "Non-Native Violations": [1, 2, 4, 4, 11, 21, 24], "Rank": 8, "Total Rank": 8, "Percentile": 0.0, "Latitude": 39.030716, "Longitude": -121.43497, "PWSID": "90605172", "Embed": ["https://plotly.com/~amotiani21/156.embed", "https://plotly.com/~amotiani21/157.embed", "https://plotly.com/~amotiani21/159.embed", "https://plotly.com/~amotiani21/161.embed"], "Checks": 0.0}, "90605126": {"Native Name": "Hoopa Valley-Wide System", "Native Violations": 0, "Non-Native Names": ["ALPHA OMEGA WINERY", "BIG SUR BAZAAR WS", "LEAPIN' LIZARD RV RANCH", "LOMA VISTA INN WS", "MESA  WATER DISTRICT", "ANCHORPOINT CHRISTIAN SCHOOL", "DEL ORO RIVER ISLAND SERV TERR #2", "BUTTE CITY COMMUNITY S.D.", "OASIS PROPERTY OWNERS ASSOCIATION", "BERRYESSA HIGHLANDS", "EAST OROSI CSD", "CANTUA CREEK VINEYARDS, IV, LLC.", "KNOLL ENTERPRISES"], "Non-Native Violations": [1, 1, 1, 2, 2, 3, 7, 8, 13, 22, 25, 26, 41], "Rank": 14, "Total Rank": 14, "Percentile": 0.0, "Latitude": 41.161505, "Longitude": -123.72444, "PWSID": "90605126", "Embed": ["https://plotly.com/~amotiani21/162.embed", "https://plotly.com/~amotiani21/163.embed", "https://plotly.com/~amotiani21/165.embed", "https://plotly.com/~amotiani21/167.embed"], "Checks": 0.0}, "90605060": {"Native Name": "Howonquet Community(Smith River)", "Native Violations": 9, "Non-Native Names": ["ALPHA OMEGA WINERY", "BIG SUR BAZAAR WS", "LEAPIN' LIZARD RV RANCH", "LOMA VISTA INN WS", "MESA  WATER DISTRICT", "ANCHORPOINT CHRISTIAN SCHOOL", "DEL ORO RIVER ISLAND SERV TERR #2", "BUTTE CITY COMMUNITY S.D.", "OASIS PROPERTY OWNERS ASSOCIATION", "BERRYESSA HIGHLANDS", "EAST OROSI CSD", "CANTUA CREEK VINEYARDS, IV, LLC.", "KNOLL ENTERPRISES"], "Non-Native Violations": [1, 1, 1, 2, 2, 3, 7, 8, 13, 22, 25, 26, 41], "Rank": 6, "Total Rank": 14, "Percentile": 57.14, "Latitude": 41.949739, "Longitude": -124.15098, "PWSID": "90605060", "Embed": ["https://plotly.com/~amotiani21/169.embed", "https://plotly.com/~amotiani21/171.embed", "https://plotly.com/~amotiani21/173.embed", "https://plotly.com/~amotiani21/175.embed"], "Checks": 9.0}, "90605109": {"Native Name": "Jackson Rancheria Casino & Hotel", "Native Violations": 0, "Non-Native Names": ["PRESTON WINERY", "ROARING CAMP", "GURNSEY AVENUE MUTUAL WATER SYSTEM", "KERN OIL AND REFINING CO.", "EB STONE", "OASIS GARDENS WATER CO.", "ELM COURT"], "Non-Native Violations": [1, 2, 4, 4, 11, 21, 24], "Rank": 8, "Total Rank": 8, "Percentile": 0.0, "Latitude": 38.359772, "Longitude": -120.75324, "PWSID": "90605109", "Embed": ["https://plotly.com/~amotiani20/3.embed", "https://plotly.com/~amotiani20/4.embed", "https://plotly.com/~amotiani20/6.embed", "https://plotly.com/~amotiani20/8.embed"], "Checks": 0.0}, "90600135": {"Native Name": "Kashia", "Native Violations": 39, "Non-Native Names": ["CAL FIRE - ISHI CONSERVATION CAMP", "7042 FOLSOM LLC WATER SYSTEM", "DIAMOND JACK'S RV RANCH", "SILVERFORK WATER ASSOCIATION", "ELKHORN REGIONAL PARK", "MATTOLE ELEMENTARY SCHOOL", "MELA'S MEXICAN RESTAURANT", "FANTESCA WINERY", "WINDY HILL WINERY", "YOSEMITE FORKS EST MUTUAL", "RIO BRAVO GREELEY SCHOOL WATER SYSTEM", "ALLENSWORTH CSD", "DUNNIGAN CHEVRON", "SHADY OAKS TRAILER RANCH", "ALPAUGH COMMUNITY SERVICES DISTRICT", "BARRY ELEMENTARY SCHOOL", "SAINT ANTHONY TRAILER PARK", "PANOCHE WATER DISTRICT"], "Non-Native Violations": [1, 2, 2, 2, 3, 3, 3, 6, 9, 9, 11, 12, 13, 14, 18, 20, 20, 22], "Rank": 1, "Total Rank": 19, "Percentile": 94.74, "Latitude": 38.480494, "Longitude": -122.74976, "PWSID": "90600135", "Embed": ["https://plotly.com/~amotiani20/10.embed", "https://plotly.com/~amotiani20/12.embed", "https://plotly.com/~amotiani20/14.embed", "https://plotly.com/~amotiani20/16.embed"], "Checks": 39.0}, "90605151": {"Native Name": "La Jolla - Third Gate Campground", "Native Violations": 0, "Non-Native Names": ["DOGWOOD BLUE JAY CYN IMP", "SACRAMENTO SIKH SOCIETY", "SUPER DRIVE IN", "VACA VILLA APARTMENTS", "EDNA BEAMAN ELEMENTARY SCHOOL", "LAKE ELEMENTARY SCHOOL", "PESCADERO HIGH SCHOOL", "SACRAMENTO SOFTBALL COMPLEX (SWS)", "NEWELL COUNTY WATER DISTRICT", "APPLE VALLEY VIEW MWC", "BASS LAKE ANNEX 3", "NORTH FORK ELEMENTARY SCHOOL", "TWIN VALLEY INC", "FCSA #34/ MILLERTON NEW TOWN", "MD 24 TEAFORD MEADOW LAKES", "FAMILY TREE FARMS", "BAR-LEN MWC", "MILLSTREAM MOBILE HOME PARK", "LEMOORE, CITY OF", "LIZZE ENTERPRISES", "FINLEYS"], "Non-Native Violations": [1, 1, 1, 1, 2, 2, 2, 2, 3, 6, 9, 11, 11, 12, 13, 17, 19, 24, 25, 27, 30], "Rank": 22, "Total Rank": 22, "Percentile": 0.0, "Latitude": 33.321881, "Longitude": -116.96499, "PWSID": "90605151", "Embed": ["https://plotly.com/~amotiani20/17.embed", "https://plotly.com/~amotiani20/18.embed", "https://plotly.com/~amotiani20/20.embed", "https://plotly.com/~amotiani20/22.embed"], "Checks": 0.0}, "90605007": {"Native Name": "La Jolla Eastern", "Native Violations": 0, "Non-Native Names": ["DOGWOOD BLUE JAY CYN IMP", "SACRAMENTO SIKH SOCIETY", "SUPER DRIVE IN", "VACA VILLA APARTMENTS", "EDNA BEAMAN ELEMENTARY SCHOOL", "LAKE ELEMENTARY SCHOOL", "PESCADERO HIGH SCHOOL", "SACRAMENTO SOFTBALL COMPLEX (SWS)", "NEWELL COUNTY WATER DISTRICT", "APPLE VALLEY VIEW MWC", "BASS LAKE ANNEX 3", "NORTH FORK ELEMENTARY SCHOOL", "TWIN VALLEY INC", "FCSA #34/ MILLERTON NEW TOWN", "MD 24 TEAFORD MEADOW LAKES", "FAMILY TREE FARMS", "BAR-LEN MWC", "MILLSTREAM MOBILE HOME PARK", "LEMOORE, CITY OF", "LIZZE ENTERPRISES", "FINLEYS"], "Non-Native Violations": [1, 1, 1, 1, 2, 2, 2, 2, 3, 6, 9, 11, 11, 12, 13, 17, 19, 24, 25, 27, 30], "Rank": 22, "Total Rank": 22, "Percentile": 0.0, "Latitude": 33.331880999999996, "Longitude": -116.96499, "PWSID": "90605007", "Embed": ["https://plotly.com/~amotiani20/23.embed", "https://plotly.com/~amotiani20/24.embed", "https://plotly.com/~amotiani20/26.embed", "https://plotly.com/~amotiani20/28.embed"], "Checks": 0.0}, "90605008": {"Native Name": "La Jolla Western", "Native Violations": 0, "Non-Native Names": ["DOGWOOD BLUE JAY CYN IMP", "SACRAMENTO SIKH SOCIETY", "SUPER DRIVE IN", "VACA VILLA APARTMENTS", "EDNA BEAMAN ELEMENTARY SCHOOL", "LAKE ELEMENTARY SCHOOL", "PESCADERO HIGH SCHOOL", "SACRAMENTO SOFTBALL COMPLEX (SWS)", "NEWELL COUNTY WATER DISTRICT", "APPLE VALLEY VIEW MWC", "BASS LAKE ANNEX 3", "NORTH FORK ELEMENTARY SCHOOL", "TWIN VALLEY INC", "FCSA #34/ MILLERTON NEW TOWN", "MD 24 TEAFORD MEADOW LAKES", "FAMILY TREE FARMS", "BAR-LEN MWC", "MILLSTREAM MOBILE HOME PARK", "LEMOORE, CITY OF", "LIZZE ENTERPRISES", "FINLEYS"], "Non-Native Violations": [1, 1, 1, 1, 2, 2, 2, 2, 3, 6, 9, 11, 11, 12, 13, 17, 19, 24, 25, 27, 30], "Rank": 22, "Total Rank": 22, "Percentile": 0.0, "Latitude": 33.341881, "Longitude": -116.96499, "PWSID": "90605008", "Embed": ["https://plotly.com/~amotiani20/29.embed", "https://plotly.com/~amotiani20/30.embed", "https://plotly.com/~amotiani20/32.embed", "https://plotly.com/~amotiani20/34.embed"], "Checks": 0.0}, "90600056": {"Native Name": "La Posta Lower Community", "Native Violations": 0, "Non-Native Names": ["EDDO'S HARBOR & R V PARK", "NATIONAL CEMENT CO.-LEBEC PLANT", "FLORISTON WATER SYSTEM", "TRACT 92  CSD", "CEMEX - ALABAMA", "THE VILLAGE MOBILE HOME PARK"], "Non-Native Violations": [1, 3, 5, 5, 13, 15], "Rank": 7, "Total Rank": 7, "Percentile": 0.0, "Latitude": 32.664307, "Longitude": -116.46513, "PWSID": "90600056", "Embed": ["https://plotly.com/~amotiani20/35.embed", "https://plotly.com/~amotiani20/36.embed", "https://plotly.com/~amotiani20/38.embed", "https://plotly.com/~amotiani20/40.embed"], "Checks": 0.0}, "90605146": {"Native Name": "La Posta Upper", "Native Violations": 2, "Non-Native Names": ["EDDO'S HARBOR & R V PARK", "NATIONAL CEMENT CO.-LEBEC PLANT", "FLORISTON WATER SYSTEM", "TRACT 92  CSD", "CEMEX - ALABAMA", "THE VILLAGE MOBILE HOME PARK"], "Non-Native Violations": [1, 3, 5, 5, 13, 15], "Rank": 6, "Total Rank": 7, "Percentile": 14.290000000000006, "Latitude": 32.794307, "Longitude": -116.36513, "PWSID": "90605146", "Embed": ["https://plotly.com/~amotiani20/42.embed", "https://plotly.com/~amotiani20/44.embed", "https://plotly.com/~amotiani20/46.embed", "https://plotly.com/~amotiani20/48.embed"], "Checks": 2.0}, "90600138": {"Native Name": "Lone Pine", "Native Violations": 44, "Non-Native Names": ["MOUNTAIN SPRINGS MUTUAL WATER COMPANY", "EAST VALLEY WATER DISTRICT", "CALISTOGA RANCH", "MOUNT WHITNEY GOLF CLUB", "GUATAY MUTUAL BENEFIT CORPORATION", "HURON, CITY OF"], "Non-Native Violations": [2, 3, 4, 11, 18, 26], "Rank": 1, "Total Rank": 7, "Percentile": 85.71000000000001, "Latitude": 36.589514, "Longitude": -118.07367, "PWSID": "90600138", "Embed": ["https://plotly.com/~amotiani20/50.embed", "https://plotly.com/~amotiani20/52.embed", "https://plotly.com/~amotiani20/54.embed", "https://plotly.com/~amotiani20/56.embed"], "Checks": 44.0}, "90605147": {"Native Name": "Los Coyotes", "Native Violations": 11, "Non-Native Names": ["DOGWOOD BLUE JAY CYN IMP", "SACRAMENTO SIKH SOCIETY", "SUPER DRIVE IN", "VACA VILLA APARTMENTS", "EDNA BEAMAN ELEMENTARY SCHOOL", "LAKE ELEMENTARY SCHOOL", "PESCADERO HIGH SCHOOL", "SACRAMENTO SOFTBALL COMPLEX (SWS)", "NEWELL COUNTY WATER DISTRICT", "APPLE VALLEY VIEW MWC", "BASS LAKE ANNEX 3", "NORTH FORK ELEMENTARY SCHOOL", "TWIN VALLEY INC", "FCSA #34/ MILLERTON NEW TOWN", "MD 24 TEAFORD MEADOW LAKES", "FAMILY TREE FARMS", "BAR-LEN MWC", "MILLSTREAM MOBILE HOME PARK", "LEMOORE, CITY OF", "LIZZE ENTERPRISES", "FINLEYS"], "Non-Native Violations": [1, 1, 1, 1, 2, 2, 2, 2, 3, 6, 9, 11, 11, 12, 13, 17, 19, 24, 25, 27, 30], "Rank": 9, "Total Rank": 22, "Percentile": 59.09, "Latitude": 33.166768, "Longitude": -116.71061, "PWSID": "90605147", "Embed": ["https://plotly.com/~amotiani20/58.embed", "https://plotly.com/~amotiani20/60.embed", "https://plotly.com/~amotiani20/62.embed", "https://plotly.com/~amotiani20/64.embed"], "Checks": 11.0}, "90600139": {"Native Name": "Manchester Rancheria", "Native Violations": 18, "Non-Native Names": ["CAL FIRE - ISHI CONSERVATION CAMP", "7042 FOLSOM LLC WATER SYSTEM", "DIAMOND JACK'S RV RANCH", "SILVERFORK WATER ASSOCIATION", "ELKHORN REGIONAL PARK", "MATTOLE ELEMENTARY SCHOOL", "MELA'S MEXICAN RESTAURANT", "FANTESCA WINERY", "WINDY HILL WINERY", "YOSEMITE FORKS EST MUTUAL", "RIO BRAVO GREELEY SCHOOL WATER SYSTEM", "ALLENSWORTH CSD", "DUNNIGAN CHEVRON", "SHADY OAKS TRAILER RANCH", "ALPAUGH COMMUNITY SERVICES DISTRICT", "BARRY ELEMENTARY SCHOOL", "SAINT ANTHONY TRAILER PARK", "PANOCHE WATER DISTRICT"], "Non-Native Violations": [1, 2, 2, 2, 3, 3, 3, 6, 9, 9, 11, 12, 13, 14, 18, 20, 20, 22], "Rank": 4, "Total Rank": 19, "Percentile": 78.95, "Latitude": 38.996389, "Longitude": -123.66468, "PWSID": "90600139", "Embed": ["https://plotly.com/~amotiani20/66.embed", "https://plotly.com/~amotiani20/68.embed", "https://plotly.com/~amotiani20/70.embed", "https://plotly.com/~amotiani20/72.embed"], "Checks": 18.0}, "90605011": {"Native Name": "Mesa Grande (Tract 2)", "Native Violations": 13, "Non-Native Names": ["DOGWOOD BLUE JAY CYN IMP", "SACRAMENTO SIKH SOCIETY", "SUPER DRIVE IN", "VACA VILLA APARTMENTS", "EDNA BEAMAN ELEMENTARY SCHOOL", "LAKE ELEMENTARY SCHOOL", "PESCADERO HIGH SCHOOL", "SACRAMENTO SOFTBALL COMPLEX (SWS)", "NEWELL COUNTY WATER DISTRICT", "APPLE VALLEY VIEW MWC", "BASS LAKE ANNEX 3", "NORTH FORK ELEMENTARY SCHOOL", "TWIN VALLEY INC", "FCSA #34/ MILLERTON NEW TOWN", "MD 24 TEAFORD MEADOW LAKES", "FAMILY TREE FARMS", "BAR-LEN MWC", "MILLSTREAM MOBILE HOME PARK", "LEMOORE, CITY OF", "LIZZE ENTERPRISES", "FINLEYS"], "Non-Native Violations": [1, 1, 1, 1, 2, 2, 2, 2, 3, 6, 9, 11, 11, 12, 13, 17, 19, 24, 25, 27, 30], "Rank": 7, "Total Rank": 22, "Percentile": 68.18, "Latitude": 33.176767999999996, "Longitude": -116.61061, "PWSID": "90605011", "Embed": ["https://plotly.com/~amotiani20/74.embed", "https://plotly.com/~amotiani20/76.embed", "https://plotly.com/~amotiani20/78.embed", "https://plotly.com/~amotiani20/80.embed"], "Checks": 13.0}, "90605132": {"Native Name": "Mesa Grande - Black Canyon", "Native Violations": 3, "Non-Native Names": ["DOGWOOD BLUE JAY CYN IMP", "SACRAMENTO SIKH SOCIETY", "SUPER DRIVE IN", "VACA VILLA APARTMENTS", "EDNA BEAMAN ELEMENTARY SCHOOL", "LAKE ELEMENTARY SCHOOL", "PESCADERO HIGH SCHOOL", "SACRAMENTO SOFTBALL COMPLEX (SWS)", "NEWELL COUNTY WATER DISTRICT", "APPLE VALLEY VIEW MWC", "BASS LAKE ANNEX 3", "NORTH FORK ELEMENTARY SCHOOL", "TWIN VALLEY INC", "FCSA #34/ MILLERTON NEW TOWN", "MD 24 TEAFORD MEADOW LAKES", "FAMILY TREE FARMS", "BAR-LEN MWC", "MILLSTREAM MOBILE HOME PARK", "LEMOORE, CITY OF", "LIZZE ENTERPRISES", "FINLEYS"], "Non-Native Violations": [1, 1, 1, 1, 2, 2, 2, 2, 3, 6, 9, 11, 11, 12, 13, 17, 19, 24, 25, 27, 30], "Rank": 13, "Total Rank": 22, "Percentile": 40.91, "Latitude": 33.306768, "Longitude": -116.71061, "PWSID": "90605132", "Embed": ["https://plotly.com/~amotiani20/82.embed", "https://plotly.com/~amotiani20/84.embed", "https://plotly.com/~amotiani20/86.embed", "https://plotly.com/~amotiani20/88.embed"], "Checks": 3.0}, "90600142": {"Native Name": "Morongo", "Native Violations": 0, "Non-Native Names": ["JACUMBA VALLEY RANCH WATER COMPANY", "99 PALMS INN AND SUITES", "LAIRD FAMILY ESTATE", "SAC VALLEY TRUCK STOP", "SHANT BHAVAN PUNJABI FUNERAL HOME", "PLAINVIEW MUTUAL WATER COMPANY", "GOOSELAKE WATER COMPANY", "RANCHO ESTATES MUTUAL WATER CO.", "STOCKTON BAPTIST CHURCH", "WINSHIP ELEMENTARY SCHOOL", "ROUND MOUNTAIN WATER COMPANY", "SIERRA EAST HOA", "OLD SUGAR MILL WINERY"], "Non-Native Violations": [1, 3, 3, 3, 4, 6, 8, 14, 17, 18, 21, 44, 76], "Rank": 14, "Total Rank": 14, "Percentile": 0.0, "Latitude": 33.920803, "Longitude": -116.87897, "PWSID": "90600142", "Embed": ["https://plotly.com/~amotiani20/89.embed", "https://plotly.com/~amotiani20/90.embed", "https://plotly.com/~amotiani20/92.embed", "https://plotly.com/~amotiani20/94.embed"], "Checks": 0.0}, "90600061": {"Native Name": "Nestle Facility Morongo", "Native Violations": 0, "Non-Native Names": ["JACUMBA VALLEY RANCH WATER COMPANY", "99 PALMS INN AND SUITES", "LAIRD FAMILY ESTATE", "SAC VALLEY TRUCK STOP", "SHANT BHAVAN PUNJABI FUNERAL HOME", "PLAINVIEW MUTUAL WATER COMPANY", "GOOSELAKE WATER COMPANY", "RANCHO ESTATES MUTUAL WATER CO.", "STOCKTON BAPTIST CHURCH", "WINSHIP ELEMENTARY SCHOOL", "ROUND MOUNTAIN WATER COMPANY", "SIERRA EAST HOA", "OLD SUGAR MILL WINERY"], "Non-Native Violations": [1, 3, 3, 3, 4, 6, 8, 14, 17, 18, 21, 44, 76], "Rank": 14, "Total Rank": 14, "Percentile": 0.0, "Latitude": 33.930803, "Longitude": -116.87897, "PWSID": "90600061", "Embed": ["https://plotly.com/~amotiani20/95.embed", "https://plotly.com/~amotiani20/96.embed", "https://plotly.com/~amotiani20/98.embed", "https://plotly.com/~amotiani20/100.embed"], "Checks": 0.0}, "90600057": {"Native Name": "Old Campo", "Native Violations": 2, "Non-Native Names": ["EDDO'S HARBOR & R V PARK", "NATIONAL CEMENT CO.-LEBEC PLANT", "FLORISTON WATER SYSTEM", "TRACT 92  CSD", "CEMEX - ALABAMA", "THE VILLAGE MOBILE HOME PARK"], "Non-Native Violations": [1, 3, 5, 5, 13, 15], "Rank": 6, "Total Rank": 7, "Percentile": 14.290000000000006, "Latitude": 32.732539, "Longitude": -116.95091, "PWSID": "90600057", "Embed": ["https://plotly.com/~amotiani20/102.embed", "https://plotly.com/~amotiani20/104.embed", "https://plotly.com/~amotiani20/106.embed", "https://plotly.com/~amotiani20/108.embed"], "Checks": 2.0}, "90605021": {"Native Name": "Original Sherwood Valley Rancheria", "Native Violations": 2, "Non-Native Names": ["CAL FIRE - ISHI CONSERVATION CAMP", "7042 FOLSOM LLC WATER SYSTEM", "DIAMOND JACK'S RV RANCH", "SILVERFORK WATER ASSOCIATION", "ELKHORN REGIONAL PARK", "MATTOLE ELEMENTARY SCHOOL", "MELA'S MEXICAN RESTAURANT", "FANTESCA WINERY", "WINDY HILL WINERY", "YOSEMITE FORKS EST MUTUAL", "RIO BRAVO GREELEY SCHOOL WATER SYSTEM", "ALLENSWORTH CSD", "DUNNIGAN CHEVRON", "SHADY OAKS TRAILER RANCH", "ALPAUGH COMMUNITY SERVICES DISTRICT", "BARRY ELEMENTARY SCHOOL", "SAINT ANTHONY TRAILER PARK", "PANOCHE WATER DISTRICT"], "Non-Native Violations": [1, 2, 2, 2, 3, 3, 3, 6, 9, 9, 11, 12, 13, 14, 18, 20, 20, 22], "Rank": 15, "Total Rank": 19, "Percentile": 21.049999999999997, "Latitude": 39.451662, "Longitude": -123.37285, "PWSID": "90605021", "Embed": ["https://plotly.com/~amotiani20/110.embed", "https://plotly.com/~amotiani20/112.embed", "https://plotly.com/~amotiani20/114.embed", "https://plotly.com/~amotiani20/116.embed"], "Checks": 2.0}, "90605153": {"Native Name": "Pala North", "Native Violations": 5, "Non-Native Names": ["DOGWOOD BLUE JAY CYN IMP", "SACRAMENTO SIKH SOCIETY", "SUPER DRIVE IN", "VACA VILLA APARTMENTS", "EDNA BEAMAN ELEMENTARY SCHOOL", "LAKE ELEMENTARY SCHOOL", "PESCADERO HIGH SCHOOL", "SACRAMENTO SOFTBALL COMPLEX (SWS)", "NEWELL COUNTY WATER DISTRICT", "APPLE VALLEY VIEW MWC", "BASS LAKE ANNEX 3", "NORTH FORK ELEMENTARY SCHOOL", "TWIN VALLEY INC", "FCSA #34/ MILLERTON NEW TOWN", "MD 24 TEAFORD MEADOW LAKES", "FAMILY TREE FARMS", "BAR-LEN MWC", "MILLSTREAM MOBILE HOME PARK", "LEMOORE, CITY OF", "LIZZE ENTERPRISES", "FINLEYS"], "Non-Native Violations": [1, 1, 1, 1, 2, 2, 2, 2, 3, 6, 9, 11, 11, 12, 13, 17, 19, 24, 25, 27, 30], "Rank": 13, "Total Rank": 22, "Percentile": 40.91, "Latitude": 33.369249, "Longitude": -117.07236, "PWSID": "90605153", "Embed": ["https://plotly.com/~amotiani20/118.embed", "https://plotly.com/~amotiani20/120.embed", "https://plotly.com/~amotiani20/122.embed", "https://plotly.com/~amotiani20/124.embed"], "Checks": 5.0}, "90600167": {"Native Name": "Pala Raceway", "Native Violations": 3, "Non-Native Names": ["DOGWOOD BLUE JAY CYN IMP", "SACRAMENTO SIKH SOCIETY", "SUPER DRIVE IN", "VACA VILLA APARTMENTS", "EDNA BEAMAN ELEMENTARY SCHOOL", "LAKE ELEMENTARY SCHOOL", "PESCADERO HIGH SCHOOL", "SACRAMENTO SOFTBALL COMPLEX (SWS)", "NEWELL COUNTY WATER DISTRICT", "APPLE VALLEY VIEW MWC", "BASS LAKE ANNEX 3", "NORTH FORK ELEMENTARY SCHOOL", "TWIN VALLEY INC", "FCSA #34/ MILLERTON NEW TOWN", "MD 24 TEAFORD MEADOW LAKES", "FAMILY TREE FARMS", "BAR-LEN MWC", "MILLSTREAM MOBILE HOME PARK", "LEMOORE, CITY OF", "LIZZE ENTERPRISES", "FINLEYS"], "Non-Native Violations": [1, 1, 1, 1, 2, 2, 2, 2, 3, 6, 9, 11, 11, 12, 13, 17, 19, 24, 25, 27, 30], "Rank": 13, "Total Rank": 22, "Percentile": 40.91, "Latitude": 33.379249, "Longitude": -117.07236, "PWSID": "90600167", "Embed": ["https://plotly.com/~amotiani20/126.embed", "https://plotly.com/~amotiani20/128.embed", "https://plotly.com/~amotiani20/130.embed", "https://plotly.com/~amotiani20/132.embed"], "Checks": 3.0}, "90600144": {"Native Name": "Pala South", "Native Violations": 5, "Non-Native Names": ["DOGWOOD BLUE JAY CYN IMP", "SACRAMENTO SIKH SOCIETY", "SUPER DRIVE IN", "VACA VILLA APARTMENTS", "EDNA BEAMAN ELEMENTARY SCHOOL", "LAKE ELEMENTARY SCHOOL", "PESCADERO HIGH SCHOOL", "SACRAMENTO SOFTBALL COMPLEX (SWS)", "NEWELL COUNTY WATER DISTRICT", "APPLE VALLEY VIEW MWC", "BASS LAKE ANNEX 3", "NORTH FORK ELEMENTARY SCHOOL", "TWIN VALLEY INC", "FCSA #34/ MILLERTON NEW TOWN", "MD 24 TEAFORD MEADOW LAKES", "FAMILY TREE FARMS", "BAR-LEN MWC", "MILLSTREAM MOBILE HOME PARK", "LEMOORE, CITY OF", "LIZZE ENTERPRISES", "FINLEYS"], "Non-Native Violations": [1, 1, 1, 1, 2, 2, 2, 2, 3, 6, 9, 11, 11, 12, 13, 17, 19, 24, 25, 27, 30], "Rank": 13, "Total Rank": 22, "Percentile": 40.91, "Latitude": 33.389249, "Longitude": -117.07236, "PWSID": "90600144", "Embed": ["https://plotly.com/~amotiani20/134.embed", "https://plotly.com/~amotiani20/136.embed", "https://plotly.com/~amotiani20/138.embed", "https://plotly.com/~amotiani20/140.embed"], "Checks": 5.0}, "90605012": {"Native Name": "Pauma", "Native Violations": 2, "Non-Native Names": ["DOGWOOD BLUE JAY CYN IMP", "SACRAMENTO SIKH SOCIETY", "SUPER DRIVE IN", "VACA VILLA APARTMENTS", "EDNA BEAMAN ELEMENTARY SCHOOL", "LAKE ELEMENTARY SCHOOL", "PESCADERO HIGH SCHOOL", "SACRAMENTO SOFTBALL COMPLEX (SWS)", "NEWELL COUNTY WATER DISTRICT", "APPLE VALLEY VIEW MWC", "BASS LAKE ANNEX 3", "NORTH FORK ELEMENTARY SCHOOL", "TWIN VALLEY INC", "FCSA #34/ MILLERTON NEW TOWN", "MD 24 TEAFORD MEADOW LAKES", "FAMILY TREE FARMS", "BAR-LEN MWC", "MILLSTREAM MOBILE HOME PARK", "LEMOORE, CITY OF", "LIZZE ENTERPRISES", "FINLEYS"], "Non-Native Violations": [1, 1, 1, 1, 2, 2, 2, 2, 3, 6, 9, 11, 11, 12, 13, 17, 19, 24, 25, 27, 30], "Rank": 14, "Total Rank": 22, "Percentile": 36.36, "Latitude": 33.311881, "Longitude": -116.96599, "PWSID": "90605012", "Embed": ["https://plotly.com/~amotiani20/142.embed", "https://plotly.com/~amotiani20/144.embed", "https://plotly.com/~amotiani20/146.embed", "https://plotly.com/~amotiani20/148.embed"], "Checks": 2.0}, "90605013": {"Native Name": "Pechanga", "Native Violations": 0, "Non-Native Names": ["PINE CREEK VILLAGE", "SOUTH KERN MUTUAL WATER COMPANY"], "Non-Native Violations": [17, 17], "Rank": 3, "Total Rank": 3, "Percentile": 0.0, "Latitude": 33.752886, "Longitude": -116.055617, "PWSID": "90605013", "Embed": ["https://plotly.com/~amotiani20/149.embed", "https://plotly.com/~amotiani20/150.embed", "https://plotly.com/~amotiani20/152.embed", "https://plotly.com/~amotiani20/154.embed"], "Checks": 0.0}, "90600399": {"Native Name": "Pit River Chimney Rock", "Native Violations": 0, "Non-Native Names": ["BARRETT JUNCTION PROPERTIES INC.", "CAMP WINACKA", "MAXVILLE LAKE WINERY", "LAKE OF THE WOODS MOBILE VILLAGE", "FRAZIER MOUNTAIN HIGH SCHOOL", "PRATHER WATER DISTRICT"], "Non-Native Violations": [1, 1, 6, 9, 15, 17], "Rank": 7, "Total Rank": 7, "Percentile": 0.0, "Latitude": 40.876184, "Longitude": -121.78975, "PWSID": "90600399", "Embed": ["https://plotly.com/~amotiani20/155.embed", "https://plotly.com/~amotiani20/156.embed", "https://plotly.com/~amotiani20/158.embed", "https://plotly.com/~amotiani20/160.embed"], "Checks": 0.0}, "90605062": {"Native Name": "Pit River Montgomery Creek Rancheria", "Native Violations": 4, "Non-Native Names": ["BARRETT JUNCTION PROPERTIES INC.", "CAMP WINACKA", "MAXVILLE LAKE WINERY", "LAKE OF THE WOODS MOBILE VILLAGE", "FRAZIER MOUNTAIN HIGH SCHOOL", "PRATHER WATER DISTRICT"], "Non-Native Violations": [1, 1, 6, 9, 15, 17], "Rank": 5, "Total Rank": 7, "Percentile": 28.569999999999993, "Latitude": 41.016184, "Longitude": -121.81975, "PWSID": "90605062", "Embed": ["https://plotly.com/~amotiani20/162.embed", "https://plotly.com/~amotiani20/164.embed", "https://plotly.com/~amotiani20/166.embed", "https://plotly.com/~amotiani20/168.embed"], "Checks": 4.0}, "90605041": {"Native Name": "Pit River XL Rancheria", "Native Violations": 1, "Non-Native Names": ["BARRETT JUNCTION PROPERTIES INC.", "CAMP WINACKA", "MAXVILLE LAKE WINERY", "LAKE OF THE WOODS MOBILE VILLAGE", "FRAZIER MOUNTAIN HIGH SCHOOL", "PRATHER WATER DISTRICT"], "Non-Native Violations": [1, 1, 6, 9, 15, 17], "Rank": 5, "Total Rank": 7, "Percentile": 28.569999999999993, "Latitude": 40.966184000000005, "Longitude": -121.94975, "PWSID": "90605041", "Embed": ["https://plotly.com/~amotiani20/170.embed", "https://plotly.com/~amotiani20/172.embed", "https://plotly.com/~amotiani20/174.embed", "https://plotly.com/~amotiani20/176.embed"], "Checks": 1.0}, "90605173": {"Native Name": "Pit Stop", "Native Violations": 1, "Non-Native Names": ["BARRETT JUNCTION PROPERTIES INC.", "CAMP WINACKA", "MAXVILLE LAKE WINERY", "LAKE OF THE WOODS MOBILE VILLAGE", "FRAZIER MOUNTAIN HIGH SCHOOL", "PRATHER WATER DISTRICT"], "Non-Native Violations": [1, 1, 6, 9, 15, 17], "Rank": 5, "Total Rank": 7, "Percentile": 28.569999999999993, "Latitude": 40.776184, "Longitude": -121.93974999999999, "PWSID": "90605173", "Embed": ["https://plotly.com/~adi10g/4.embed", "https://plotly.com/~adi10g/6.embed", "https://plotly.com/~adi10g/8.embed", "https://plotly.com/~adi10g/10.embed"], "Checks": 1.0}, "90600145": {"Native Name": "Point Arena Rancheria", "Native Violations": 21, "Non-Native Names": ["CAL FIRE - ISHI CONSERVATION CAMP", "7042 FOLSOM LLC WATER SYSTEM", "DIAMOND JACK'S RV RANCH", "SILVERFORK WATER ASSOCIATION", "ELKHORN REGIONAL PARK", "MATTOLE ELEMENTARY SCHOOL", "MELA'S MEXICAN RESTAURANT", "FANTESCA WINERY", "WINDY HILL WINERY", "YOSEMITE FORKS EST MUTUAL", "RIO BRAVO GREELEY SCHOOL WATER SYSTEM", "ALLENSWORTH CSD", "DUNNIGAN CHEVRON", "SHADY OAKS TRAILER RANCH", "ALPAUGH COMMUNITY SERVICES DISTRICT", "BARRY ELEMENTARY SCHOOL", "SAINT ANTHONY TRAILER PARK", "PANOCHE WATER DISTRICT"], "Non-Native Violations": [1, 2, 2, 2, 3, 3, 3, 6, 9, 9, 11, 12, 13, 14, 18, 20, 20, 22], "Rank": 2, "Total Rank": 19, "Percentile": 89.47, "Latitude": 38.898385, "Longitude": -123.65746, "PWSID": "90600145", "Embed": ["https://plotly.com/~adi10g/12.embed", "https://plotly.com/~adi10g/14.embed", "https://plotly.com/~adi10g/16.embed", "https://plotly.com/~adi10g/18.embed"], "Checks": 21.0}, "90400679": {"Native Name": "Quechan Casino Resort", "Native Violations": 7, "Non-Native Names": ["JACUMBA VALLEY RANCH WATER COMPANY", "99 PALMS INN AND SUITES", "LAIRD FAMILY ESTATE", "SAC VALLEY TRUCK STOP", "SHANT BHAVAN PUNJABI FUNERAL HOME", "PLAINVIEW MUTUAL WATER COMPANY", "GOOSELAKE WATER COMPANY", "RANCHO ESTATES MUTUAL WATER CO.", "STOCKTON BAPTIST CHURCH", "WINSHIP ELEMENTARY SCHOOL", "ROUND MOUNTAIN WATER COMPANY", "SIERRA EAST HOA", "OLD SUGAR MILL WINERY"], "Non-Native Violations": [1, 3, 3, 3, 4, 6, 8, 14, 17, 18, 21, 44, 76], "Rank": 8, "Total Rank": 14, "Percentile": 42.86, "Latitude": 32.786759, "Longitude": -114.62591, "PWSID": "90400679", "Embed": ["https://plotly.com/~adi10g/20.embed", "https://plotly.com/~adi10g/22.embed", "https://plotly.com/~adi10g/24.embed", "https://plotly.com/~adi10g/26.embed"], "Checks": 7.0}, "90400089": {"Native Name": "Quechan Utility", "Native Violations": 200, "Non-Native Names": ["JACUMBA VALLEY RANCH WATER COMPANY", "99 PALMS INN AND SUITES", "LAIRD FAMILY ESTATE", "SAC VALLEY TRUCK STOP", "SHANT BHAVAN PUNJABI FUNERAL HOME", "PLAINVIEW MUTUAL WATER COMPANY", "GOOSELAKE WATER COMPANY", "RANCHO ESTATES MUTUAL WATER CO.", "STOCKTON BAPTIST CHURCH", "WINSHIP ELEMENTARY SCHOOL", "ROUND MOUNTAIN WATER COMPANY", "SIERRA EAST HOA", "OLD SUGAR MILL WINERY"], "Non-Native Violations": [1, 3, 3, 3, 4, 6, 8, 14, 17, 18, 21, 44, 76], "Rank": 1, "Total Rank": 14, "Percentile": 92.86, "Latitude": 32.796759, "Longitude": -114.62591, "PWSID": "90400089", "Embed": ["https://plotly.com/~adi10g/28.embed", "https://plotly.com/~adi10g/30.embed", "https://plotly.com/~adi10g/32.embed", "https://plotly.com/~adi10g/34.embed"], "Checks": 200.0}, "90600058": {"Native Name": "Red Hawk Casino - Shingle Springs", "Native Violations": 1, "Non-Native Names": ["PRESTON WINERY", "ROARING CAMP", "GURNSEY AVENUE MUTUAL WATER SYSTEM", "KERN OIL AND REFINING CO.", "EB STONE", "OASIS GARDENS WATER CO.", "ELM COURT"], "Non-Native Violations": [1, 2, 4, 4, 11, 21, 24], "Rank": 7, "Total Rank": 8, "Percentile": 12.5, "Latitude": 38.724682, "Longitude": -120.79533, "PWSID": "90600058", "Embed": ["https://plotly.com/~adi10g/36.embed", "https://plotly.com/~adi10g/38.embed", "https://plotly.com/~adi10g/40.embed", "https://plotly.com/~adi10g/42.embed"], "Checks": 1.0}, "90605083": {"Native Name": "Redding Rancheria", "Native Violations": 12, "Non-Native Names": ["BARRETT JUNCTION PROPERTIES INC.", "CAMP WINACKA", "MAXVILLE LAKE WINERY", "LAKE OF THE WOODS MOBILE VILLAGE", "FRAZIER MOUNTAIN HIGH SCHOOL", "PRATHER WATER DISTRICT"], "Non-Native Violations": [1, 1, 6, 9, 15, 17], "Rank": 3, "Total Rank": 7, "Percentile": 57.14, "Latitude": 40.56816, "Longitude": -122.41519, "PWSID": "90605083", "Embed": ["https://plotly.com/~adi10g/44.embed", "https://plotly.com/~adi10g/46.embed", "https://plotly.com/~adi10g/48.embed", "https://plotly.com/~adi10g/50.embed"], "Checks": 12.0}, "90605118": {"Native Name": "Redwood Valley Rancheria", "Native Violations": 2, "Non-Native Names": ["CAL FIRE - ISHI CONSERVATION CAMP", "7042 FOLSOM LLC WATER SYSTEM", "DIAMOND JACK'S RV RANCH", "SILVERFORK WATER ASSOCIATION", "ELKHORN REGIONAL PARK", "MATTOLE ELEMENTARY SCHOOL", "MELA'S MEXICAN RESTAURANT", "FANTESCA WINERY", "WINDY HILL WINERY", "YOSEMITE FORKS EST MUTUAL", "RIO BRAVO GREELEY SCHOOL WATER SYSTEM", "ALLENSWORTH CSD", "DUNNIGAN CHEVRON", "SHADY OAKS TRAILER RANCH", "ALPAUGH COMMUNITY SERVICES DISTRICT", "BARRY ELEMENTARY SCHOOL", "SAINT ANTHONY TRAILER PARK", "PANOCHE WATER DISTRICT"], "Non-Native Violations": [1, 2, 2, 2, 3, 3, 3, 6, 9, 9, 11, 12, 13, 14, 18, 20, 20, 22], "Rank": 15, "Total Rank": 19, "Percentile": 21.049999999999997, "Latitude": 39.285782, "Longitude": -123.22064, "PWSID": "90605118", "Embed": ["https://plotly.com/~adi10g/52.embed", "https://plotly.com/~adi10g/54.embed", "https://plotly.com/~adi10g/56.embed", "https://plotly.com/~adi10g/58.embed"], "Checks": 2.0}, "90605057": {"Native Name": "Resighini Rancheria", "Native Violations": 0, "Non-Native Names": ["ALPHA OMEGA WINERY", "BIG SUR BAZAAR WS", "LEAPIN' LIZARD RV RANCH", "LOMA VISTA INN WS", "MESA  WATER DISTRICT", "ANCHORPOINT CHRISTIAN SCHOOL", "DEL ORO RIVER ISLAND SERV TERR #2", "BUTTE CITY COMMUNITY S.D.", "OASIS PROPERTY OWNERS ASSOCIATION", "BERRYESSA HIGHLANDS", "EAST OROSI CSD", "CANTUA CREEK VINEYARDS, IV, LLC.", "KNOLL ENTERPRISES"], "Non-Native Violations": [1, 1, 1, 2, 2, 3, 7, 8, 13, 22, 25, 26, 41], "Rank": 14, "Total Rank": 14, "Percentile": 0.0, "Latitude": 41.51823, "Longitude": -124.03075, "PWSID": "90605057", "Embed": ["https://plotly.com/~adi10g/59.embed", "https://plotly.com/~adi10g/60.embed", "https://plotly.com/~adi10g/62.embed", "https://plotly.com/~adi10g/64.embed"], "Checks": 0.0}, "90600147": {"Native Name": "Rincon Northern", "Native Violations": 1, "Non-Native Names": ["DOGWOOD BLUE JAY CYN IMP", "SACRAMENTO SIKH SOCIETY", "SUPER DRIVE IN", "VACA VILLA APARTMENTS", "EDNA BEAMAN ELEMENTARY SCHOOL", "LAKE ELEMENTARY SCHOOL", "PESCADERO HIGH SCHOOL", "SACRAMENTO SOFTBALL COMPLEX (SWS)", "NEWELL COUNTY WATER DISTRICT", "APPLE VALLEY VIEW MWC", "BASS LAKE ANNEX 3", "NORTH FORK ELEMENTARY SCHOOL", "TWIN VALLEY INC", "FCSA #34/ MILLERTON NEW TOWN", "MD 24 TEAFORD MEADOW LAKES", "FAMILY TREE FARMS", "BAR-LEN MWC", "MILLSTREAM MOBILE HOME PARK", "LEMOORE, CITY OF", "LIZZE ENTERPRISES", "FINLEYS"], "Non-Native Violations": [1, 1, 1, 1, 2, 2, 2, 2, 3, 6, 9, 11, 11, 12, 13, 17, 19, 24, 25, 27, 30], "Rank": 18, "Total Rank": 22, "Percentile": 18.180000000000007, "Latitude": 33.261748, "Longitude": -117.01027, "PWSID": "90600147", "Embed": ["https://plotly.com/~adi10g/66.embed", "https://plotly.com/~adi10g/68.embed", "https://plotly.com/~adi10g/70.embed", "https://plotly.com/~adi10g/72.embed"], "Checks": 1.0}, "90600146": {"Native Name": "Rincon Paradise Creek", "Native Violations": 1, "Non-Native Names": ["DOGWOOD BLUE JAY CYN IMP", "SACRAMENTO SIKH SOCIETY", "SUPER DRIVE IN", "VACA VILLA APARTMENTS", "EDNA BEAMAN ELEMENTARY SCHOOL", "LAKE ELEMENTARY SCHOOL", "PESCADERO HIGH SCHOOL", "SACRAMENTO SOFTBALL COMPLEX (SWS)", "NEWELL COUNTY WATER DISTRICT", "APPLE VALLEY VIEW MWC", "BASS LAKE ANNEX 3", "NORTH FORK ELEMENTARY SCHOOL", "TWIN VALLEY INC", "FCSA #34/ MILLERTON NEW TOWN", "MD 24 TEAFORD MEADOW LAKES", "FAMILY TREE FARMS", "BAR-LEN MWC", "MILLSTREAM MOBILE HOME PARK", "LEMOORE, CITY OF", "LIZZE ENTERPRISES", "FINLEYS"], "Non-Native Violations": [1, 1, 1, 1, 2, 2, 2, 2, 3, 6, 9, 11, 11, 12, 13, 17, 19, 24, 25, 27, 30], "Rank": 18, "Total Rank": 22, "Percentile": 18.180000000000007, "Latitude": 33.311747999999994, "Longitude": -117.04027, "PWSID": "90600146", "Embed": ["https://plotly.com/~adi10g/74.embed", "https://plotly.com/~adi10g/76.embed", "https://plotly.com/~adi10g/78.embed", "https://plotly.com/~adi10g/80.embed"], "Checks": 1.0}, "90605171": {"Native Name": "Robinson Rancheria Gas Station", "Native Violations": 1, "Non-Native Names": ["CAL FIRE - ISHI CONSERVATION CAMP", "7042 FOLSOM LLC WATER SYSTEM", "DIAMOND JACK'S RV RANCH", "SILVERFORK WATER ASSOCIATION", "ELKHORN REGIONAL PARK", "MATTOLE ELEMENTARY SCHOOL", "MELA'S MEXICAN RESTAURANT", "FANTESCA WINERY", "WINDY HILL WINERY", "YOSEMITE FORKS EST MUTUAL", "RIO BRAVO GREELEY SCHOOL WATER SYSTEM", "ALLENSWORTH CSD", "DUNNIGAN CHEVRON", "SHADY OAKS TRAILER RANCH", "ALPAUGH COMMUNITY SERVICES DISTRICT", "BARRY ELEMENTARY SCHOOL", "SAINT ANTHONY TRAILER PARK", "PANOCHE WATER DISTRICT"], "Non-Native Violations": [1, 2, 2, 2, 3, 3, 3, 6, 9, 9, 11, 12, 13, 14, 18, 20, 20, 22], "Rank": 18, "Total Rank": 19, "Percentile": 5.260000000000005, "Latitude": 39.172397, "Longitude": -122.90474, "PWSID": "90605171", "Embed": ["https://plotly.com/~adi10g/82.embed", "https://plotly.com/~adi10g/84.embed", "https://plotly.com/~adi10g/86.embed", "https://plotly.com/~adi10g/88.embed"], "Checks": 1.0}, "90600052": {"Native Name": "Rolling Hills Casino", "Native Violations": 0, "Non-Native Names": ["BARRETT JUNCTION PROPERTIES INC.", "CAMP WINACKA", "MAXVILLE LAKE WINERY", "LAKE OF THE WOODS MOBILE VILLAGE", "FRAZIER MOUNTAIN HIGH SCHOOL", "PRATHER WATER DISTRICT"], "Non-Native Violations": [1, 1, 6, 9, 15, 17], "Rank": 7, "Total Rank": 7, "Percentile": 0.0, "Latitude": 39.918271, "Longitude": -122.21393, "PWSID": "90600052", "Embed": ["https://plotly.com/~adi10g/89.embed", "https://plotly.com/~adi10g/90.embed", "https://plotly.com/~adi10g/92.embed", "https://plotly.com/~adi10g/94.embed"], "Checks": 0.0}, "90605128": {"Native Name": "Round Valley Admin. Complex", "Native Violations": 3, "Non-Native Names": ["CAL FIRE - ISHI CONSERVATION CAMP", "7042 FOLSOM LLC WATER SYSTEM", "DIAMOND JACK'S RV RANCH", "SILVERFORK WATER ASSOCIATION", "ELKHORN REGIONAL PARK", "MATTOLE ELEMENTARY SCHOOL", "MELA'S MEXICAN RESTAURANT", "FANTESCA WINERY", "WINDY HILL WINERY", "YOSEMITE FORKS EST MUTUAL", "RIO BRAVO GREELEY SCHOOL WATER SYSTEM", "ALLENSWORTH CSD", "DUNNIGAN CHEVRON", "SHADY OAKS TRAILER RANCH", "ALPAUGH COMMUNITY SERVICES DISTRICT", "BARRY ELEMENTARY SCHOOL", "SAINT ANTHONY TRAILER PARK", "PANOCHE WATER DISTRICT"], "Non-Native Violations": [1, 2, 2, 2, 3, 3, 3, 6, 9, 9, 11, 12, 13, 14, 18, 20, 20, 22], "Rank": 12, "Total Rank": 19, "Percentile": 36.84, "Latitude": 39.925781, "Longitude": -123.23026, "PWSID": "90605128", "Embed": ["https://plotly.com/~adi10g/96.embed", "https://plotly.com/~adi10g/98.embed", "https://plotly.com/~adi10g/100.embed", "https://plotly.com/~adi10g/102.embed"], "Checks": 3.0}, "90605073": {"Native Name": "Round Valley Agency", "Native Violations": 1, "Non-Native Names": ["CAL FIRE - ISHI CONSERVATION CAMP", "7042 FOLSOM LLC WATER SYSTEM", "DIAMOND JACK'S RV RANCH", "SILVERFORK WATER ASSOCIATION", "ELKHORN REGIONAL PARK", "MATTOLE ELEMENTARY SCHOOL", "MELA'S MEXICAN RESTAURANT", "FANTESCA WINERY", "WINDY HILL WINERY", "YOSEMITE FORKS EST MUTUAL", "RIO BRAVO GREELEY SCHOOL WATER SYSTEM", "ALLENSWORTH CSD", "DUNNIGAN CHEVRON", "SHADY OAKS TRAILER RANCH", "ALPAUGH COMMUNITY SERVICES DISTRICT", "BARRY ELEMENTARY SCHOOL", "SAINT ANTHONY TRAILER PARK", "PANOCHE WATER DISTRICT"], "Non-Native Violations": [1, 2, 2, 2, 3, 3, 3, 6, 9, 9, 11, 12, 13, 14, 18, 20, 20, 22], "Rank": 18, "Total Rank": 19, "Percentile": 5.260000000000005, "Latitude": 39.825781, "Longitude": -123.23026, "PWSID": "90605073", "Embed": ["https://plotly.com/~adi10g/104.embed", "https://plotly.com/~adi10g/106.embed", "https://plotly.com/~adi10g/108.embed", "https://plotly.com/~adi10g/110.embed"], "Checks": 1.0}, "90605113": {"Native Name": "Round Valley Health Clinic", "Native Violations": 87, "Non-Native Names": ["CAL FIRE - ISHI CONSERVATION CAMP", "7042 FOLSOM LLC WATER SYSTEM", "DIAMOND JACK'S RV RANCH", "SILVERFORK WATER ASSOCIATION", "ELKHORN REGIONAL PARK", "MATTOLE ELEMENTARY SCHOOL", "MELA'S MEXICAN RESTAURANT", "FANTESCA WINERY", "WINDY HILL WINERY", "YOSEMITE FORKS EST MUTUAL", "RIO BRAVO GREELEY SCHOOL WATER SYSTEM", "ALLENSWORTH CSD", "DUNNIGAN CHEVRON", "SHADY OAKS TRAILER RANCH", "ALPAUGH COMMUNITY SERVICES DISTRICT", "BARRY ELEMENTARY SCHOOL", "SAINT ANTHONY TRAILER PARK", "PANOCHE WATER DISTRICT"], "Non-Native Violations": [1, 2, 2, 2, 3, 3, 3, 6, 9, 9, 11, 12, 13, 14, 18, 20, 20, 22], "Rank": 1, "Total Rank": 19, "Percentile": 94.74, "Latitude": 39.885781, "Longitude": -123.20026, "PWSID": "90605113", "Embed": ["https://plotly.com/~adi10g/112.embed", "https://plotly.com/~adi10g/114.embed", "https://plotly.com/~adi10g/116.embed", "https://plotly.com/~adi10g/118.embed"], "Checks": 87.0}, "90605177": {"Native Name": "Round Valley Hidden Oaks Casino and Restaurant", "Native Violations": 4, "Non-Native Names": ["CAL FIRE - ISHI CONSERVATION CAMP", "7042 FOLSOM LLC WATER SYSTEM", "DIAMOND JACK'S RV RANCH", "SILVERFORK WATER ASSOCIATION", "ELKHORN REGIONAL PARK", "MATTOLE ELEMENTARY SCHOOL", "MELA'S MEXICAN RESTAURANT", "FANTESCA WINERY", "WINDY HILL WINERY", "YOSEMITE FORKS EST MUTUAL", "RIO BRAVO GREELEY SCHOOL WATER SYSTEM", "ALLENSWORTH CSD", "DUNNIGAN CHEVRON", "SHADY OAKS TRAILER RANCH", "ALPAUGH COMMUNITY SERVICES DISTRICT", "BARRY ELEMENTARY SCHOOL", "SAINT ANTHONY TRAILER PARK", "PANOCHE WATER DISTRICT"], "Non-Native Violations": [1, 2, 2, 2, 3, 3, 3, 6, 9, 9, 11, 12, 13, 14, 18, 20, 20, 22], "Rank": 12, "Total Rank": 19, "Percentile": 36.84, "Latitude": 39.815781, "Longitude": -123.25026, "PWSID": "90605177", "Embed": [null, null, "https://plotly.com/~adi10g/120.embed", "https://plotly.com/~adi10g/122.embed"], "Checks": 4.0}, "90605015": {"Native Name": "Round Valley Piner", "Native Violations": 0, "Non-Native Names": ["CAL FIRE - ISHI CONSERVATION CAMP", "7042 FOLSOM LLC WATER SYSTEM", "DIAMOND JACK'S RV RANCH", "SILVERFORK WATER ASSOCIATION", "ELKHORN REGIONAL PARK", "MATTOLE ELEMENTARY SCHOOL", "MELA'S MEXICAN RESTAURANT", "FANTESCA WINERY", "WINDY HILL WINERY", "YOSEMITE FORKS EST MUTUAL", "RIO BRAVO GREELEY SCHOOL WATER SYSTEM", "ALLENSWORTH CSD", "DUNNIGAN CHEVRON", "SHADY OAKS TRAILER RANCH", "ALPAUGH COMMUNITY SERVICES DISTRICT", "BARRY ELEMENTARY SCHOOL", "SAINT ANTHONY TRAILER PARK", "PANOCHE WATER DISTRICT"], "Non-Native Violations": [1, 2, 2, 2, 3, 3, 3, 6, 9, 9, 11, 12, 13, 14, 18, 20, 20, 22], "Rank": 19, "Total Rank": 19, "Percentile": 0.0, "Latitude": 39.845781, "Longitude": -123.22026, "PWSID": "90605015", "Embed": ["https://plotly.com/~adi10g/123.embed", "https://plotly.com/~adi10g/124.embed", "https://plotly.com/~adi10g/126.embed", "https://plotly.com/~adi10g/128.embed"], "Checks": 0.0}, "90605000": {"Native Name": "Running Creek Casino Water System (Habematolel)", "Native Violations": 0, "Non-Native Names": ["CAL FIRE - ISHI CONSERVATION CAMP", "7042 FOLSOM LLC WATER SYSTEM", "DIAMOND JACK'S RV RANCH", "SILVERFORK WATER ASSOCIATION", "ELKHORN REGIONAL PARK", "MATTOLE ELEMENTARY SCHOOL", "MELA'S MEXICAN RESTAURANT", "FANTESCA WINERY", "WINDY HILL WINERY", "YOSEMITE FORKS EST MUTUAL", "RIO BRAVO GREELEY SCHOOL WATER SYSTEM", "ALLENSWORTH CSD", "DUNNIGAN CHEVRON", "SHADY OAKS TRAILER RANCH", "ALPAUGH COMMUNITY SERVICES DISTRICT", "BARRY ELEMENTARY SCHOOL", "SAINT ANTHONY TRAILER PARK", "PANOCHE WATER DISTRICT"], "Non-Native Violations": [1, 2, 2, 2, 3, 3, 3, 6, 9, 9, 11, 12, 13, 14, 18, 20, 20, 22], "Rank": 19, "Total Rank": 19, "Percentile": 0.0, "Latitude": 39.172397, "Longitude": -122.91474, "PWSID": "90605000", "Embed": ["https://plotly.com/~adi10g/129.embed", "https://plotly.com/~adi10g/130.embed", "https://plotly.com/~adi10g/132.embed", "https://plotly.com/~adi10g/134.embed"], "Checks": 0.0}, "90605017": {"Native Name": "San Pasqual District A", "Native Violations": 0, "Non-Native Names": ["DOGWOOD BLUE JAY CYN IMP", "SACRAMENTO SIKH SOCIETY", "SUPER DRIVE IN", "VACA VILLA APARTMENTS", "EDNA BEAMAN ELEMENTARY SCHOOL", "LAKE ELEMENTARY SCHOOL", "PESCADERO HIGH SCHOOL", "SACRAMENTO SOFTBALL COMPLEX (SWS)", "NEWELL COUNTY WATER DISTRICT", "APPLE VALLEY VIEW MWC", "BASS LAKE ANNEX 3", "NORTH FORK ELEMENTARY SCHOOL", "TWIN VALLEY INC", "FCSA #34/ MILLERTON NEW TOWN", "MD 24 TEAFORD MEADOW LAKES", "FAMILY TREE FARMS", "BAR-LEN MWC", "MILLSTREAM MOBILE HOME PARK", "LEMOORE, CITY OF", "LIZZE ENTERPRISES", "FINLEYS"], "Non-Native Violations": [1, 1, 1, 1, 2, 2, 2, 2, 3, 6, 9, 11, 11, 12, 13, 17, 19, 24, 25, 27, 30], "Rank": 22, "Total Rank": 22, "Percentile": 0.0, "Latitude": 33.142706, "Longitude": -117.03049, "PWSID": "90605017", "Embed": ["https://plotly.com/~adi10g/135.embed", "https://plotly.com/~adi10g/136.embed", "https://plotly.com/~adi10g/138.embed", "https://plotly.com/~adi10g/140.embed"], "Checks": 0.0}, "90605080": {"Native Name": "San Pasqual District B", "Native Violations": 0, "Non-Native Names": ["DOGWOOD BLUE JAY CYN IMP", "SACRAMENTO SIKH SOCIETY", "SUPER DRIVE IN", "VACA VILLA APARTMENTS", "EDNA BEAMAN ELEMENTARY SCHOOL", "LAKE ELEMENTARY SCHOOL", "PESCADERO HIGH SCHOOL", "SACRAMENTO SOFTBALL COMPLEX (SWS)", "NEWELL COUNTY WATER DISTRICT", "APPLE VALLEY VIEW MWC", "BASS LAKE ANNEX 3", "NORTH FORK ELEMENTARY SCHOOL", "TWIN VALLEY INC", "FCSA #34/ MILLERTON NEW TOWN", "MD 24 TEAFORD MEADOW LAKES", "FAMILY TREE FARMS", "BAR-LEN MWC", "MILLSTREAM MOBILE HOME PARK", "LEMOORE, CITY OF", "LIZZE ENTERPRISES", "FINLEYS"], "Non-Native Violations": [1, 1, 1, 1, 2, 2, 2, 2, 3, 6, 9, 11, 11, 12, 13, 17, 19, 24, 25, 27, 30], "Rank": 22, "Total Rank": 22, "Percentile": 0.0, "Latitude": 33.192706, "Longitude": -117.13049, "PWSID": "90605080", "Embed": ["https://plotly.com/~adi10g/141.embed", "https://plotly.com/~adi10g/142.embed", "https://plotly.com/~adi10g/144.embed", "https://plotly.com/~adi10g/146.embed"], "Checks": 0.0}, "90600148": {"Native Name": "Santa Rosa Rancheria", "Native Violations": 3, "Non-Native Names": ["PINE VALLEY BIBLE CONFERENCE CENTER", "ESCALON GOLF COURSE WS", "PIGEON POINT YOUTH HOSTEL", "INTERSTATE TRUCK CENTER VALLEY PETERBILT", "FCSA #30/EL PORVENIR"], "Non-Native Violations": [2, 3, 3, 17, 33], "Rank": 3, "Total Rank": 6, "Percentile": 50.0, "Latitude": 36.312075, "Longitude": -119.87349, "PWSID": "90600148", "Embed": ["https://plotly.com/~adi10g/148.embed", "https://plotly.com/~adi10g/150.embed", "https://plotly.com/~adi10g/152.embed", "https://plotly.com/~adi10g/154.embed"], "Checks": 3.0}, "90605019": {"Native Name": "Santa Rosa Reservation", "Native Violations": 9, "Non-Native Names": ["PINE VALLEY BIBLE CONFERENCE CENTER", "ESCALON GOLF COURSE WS", "PIGEON POINT YOUTH HOSTEL", "INTERSTATE TRUCK CENTER VALLEY PETERBILT", "FCSA #30/EL PORVENIR"], "Non-Native Violations": [2, 3, 3, 17, 33], "Rank": 3, "Total Rank": 6, "Percentile": 50.0, "Latitude": 36.322075, "Longitude": -119.75349, "PWSID": "90605019", "Embed": ["https://plotly.com/~adi10g/156.embed", "https://plotly.com/~adi10g/158.embed", "https://plotly.com/~adi10g/160.embed", "https://plotly.com/~adi10g/162.embed"], "Checks": 9.0}, "90605136": {"Native Name": "Santa Rosa Tachi Palace", "Native Violations": 2, "Non-Native Names": ["PINE VALLEY BIBLE CONFERENCE CENTER", "ESCALON GOLF COURSE WS", "PIGEON POINT YOUTH HOSTEL", "INTERSTATE TRUCK CENTER VALLEY PETERBILT", "FCSA #30/EL PORVENIR"], "Non-Native Violations": [2, 3, 3, 17, 33], "Rank": 5, "Total Rank": 6, "Percentile": 16.67, "Latitude": 36.492075, "Longitude": -119.80349, "PWSID": "90605136", "Embed": ["https://plotly.com/~adi10g/164.embed", "https://plotly.com/~adi10g/166.embed", "https://plotly.com/~adi10g/168.embed", "https://plotly.com/~adi10g/170.embed"], "Checks": 2.0}, "90605020": {"Native Name": "Santa Ysabel Canyon", "Native Violations": 2, "Non-Native Names": ["DOGWOOD BLUE JAY CYN IMP", "SACRAMENTO SIKH SOCIETY", "SUPER DRIVE IN", "VACA VILLA APARTMENTS", "EDNA BEAMAN ELEMENTARY SCHOOL", "LAKE ELEMENTARY SCHOOL", "PESCADERO HIGH SCHOOL", "SACRAMENTO SOFTBALL COMPLEX (SWS)", "NEWELL COUNTY WATER DISTRICT", "APPLE VALLEY VIEW MWC", "BASS LAKE ANNEX 3", "NORTH FORK ELEMENTARY SCHOOL", "TWIN VALLEY INC", "FCSA #34/ MILLERTON NEW TOWN", "MD 24 TEAFORD MEADOW LAKES", "FAMILY TREE FARMS", "BAR-LEN MWC", "MILLSTREAM MOBILE HOME PARK", "LEMOORE, CITY OF", "LIZZE ENTERPRISES", "FINLEYS"], "Non-Native Violations": [1, 1, 1, 1, 2, 2, 2, 2, 3, 6, 9, 11, 11, 12, 13, 17, 19, 24, 25, 27, 30], "Rank": 14, "Total Rank": 22, "Percentile": 36.36, "Latitude": 33.236768, "Longitude": -116.74061, "PWSID": "90605020", "Embed": ["https://plotly.com/~adi10g/172.embed", "https://plotly.com/~adi10g/174.embed", "https://plotly.com/~adi10g/176.embed", "https://plotly.com/~adi10g/178.embed"], "Checks": 2.0}, "90600150": {"Native Name": "Santa Ysabel Main", "Native Violations": 3, "Non-Native Names": ["DOGWOOD BLUE JAY CYN IMP", "SACRAMENTO SIKH SOCIETY", "SUPER DRIVE IN", "VACA VILLA APARTMENTS", "EDNA BEAMAN ELEMENTARY SCHOOL", "LAKE ELEMENTARY SCHOOL", "PESCADERO HIGH SCHOOL", "SACRAMENTO SOFTBALL COMPLEX (SWS)", "NEWELL COUNTY WATER DISTRICT", "APPLE VALLEY VIEW MWC", "BASS LAKE ANNEX 3", "NORTH FORK ELEMENTARY SCHOOL", "TWIN VALLEY INC", "FCSA #34/ MILLERTON NEW TOWN", "MD 24 TEAFORD MEADOW LAKES", "FAMILY TREE FARMS", "BAR-LEN MWC", "MILLSTREAM MOBILE HOME PARK", "LEMOORE, CITY OF", "LIZZE ENTERPRISES", "FINLEYS"], "Non-Native Violations": [1, 1, 1, 1, 2, 2, 2, 2, 3, 6, 9, 11, 11, 12, 13, 17, 19, 24, 25, 27, 30], "Rank": 13, "Total Rank": 22, "Percentile": 40.91, "Latitude": 33.136768, "Longitude": -116.71061, "PWSID": "90600150", "Embed": ["https://plotly.com/~adi10g/180.embed", "https://plotly.com/~adi10g/182.embed", "https://plotly.com/~adi10g/184.embed", "https://plotly.com/~adi10g/186.embed"], "Checks": 3.0}, "90600133": {"Native Name": "Shanel Tribal Utility District", "Native Violations": 1, "Non-Native Names": ["CAL FIRE - ISHI CONSERVATION CAMP", "7042 FOLSOM LLC WATER SYSTEM", "DIAMOND JACK'S RV RANCH", "SILVERFORK WATER ASSOCIATION", "ELKHORN REGIONAL PARK", "MATTOLE ELEMENTARY SCHOOL", "MELA'S MEXICAN RESTAURANT", "FANTESCA WINERY", "WINDY HILL WINERY", "YOSEMITE FORKS EST MUTUAL", "RIO BRAVO GREELEY SCHOOL WATER SYSTEM", "ALLENSWORTH CSD", "DUNNIGAN CHEVRON", "SHADY OAKS TRAILER RANCH", "ALPAUGH COMMUNITY SERVICES DISTRICT", "BARRY ELEMENTARY SCHOOL", "SAINT ANTHONY TRAILER PARK", "PANOCHE WATER DISTRICT"], "Non-Native Violations": [1, 2, 2, 2, 3, 3, 3, 6, 9, 9, 11, 12, 13, 14, 18, 20, 20, 22], "Rank": 18, "Total Rank": 19, "Percentile": 5.260000000000005, "Latitude": 38.955142, "Longitude": -123.08125, "PWSID": "90600133", "Embed": ["https://plotly.com/~arnav10g/7.embed", "https://plotly.com/~arnav10g/9.embed", "https://plotly.com/~arnav10g/5.embed", "https://plotly.com/~arnav10g/12.embed"], "Checks": 1.0}, "90600151": {"Native Name": "Soboba", "Native Violations": 7, "Non-Native Names": ["PINE CREEK VILLAGE", "SOUTH KERN MUTUAL WATER COMPANY"], "Non-Native Violations": [17, 17], "Rank": 3, "Total Rank": 3, "Percentile": 0.0, "Latitude": 33.788491, "Longitude": -116.95125, "PWSID": "90600151", "Embed": ["https://plotly.com/~arnav10g/14.embed", "https://plotly.com/~arnav10g/16.embed", "https://plotly.com/~arnav10g/18.embed", "https://plotly.com/~arnav10g/20.embed"], "Checks": 7.0}, "90600059": {"Native Name": "South Campo", "Native Violations": 2, "Non-Native Names": ["EDDO'S HARBOR & R V PARK", "NATIONAL CEMENT CO.-LEBEC PLANT", "FLORISTON WATER SYSTEM", "TRACT 92  CSD", "CEMEX - ALABAMA", "THE VILLAGE MOBILE HOME PARK"], "Non-Native Violations": [1, 3, 5, 5, 13, 15], "Rank": 6, "Total Rank": 7, "Percentile": 14.290000000000006, "Latitude": 32.664307, "Longitude": -116.46513, "PWSID": "90600059", "Embed": ["https://plotly.com/~arnav10g/22.embed", "https://plotly.com/~arnav10g/24.embed", "https://plotly.com/~arnav10g/26.embed", "https://plotly.com/~arnav10g/28.embed"], "Checks": 2.0}, "90600160": {"Native Name": "Stewart Village", "Native Violations": 11, "Non-Native Names": ["MOUNTAIN SPRINGS MUTUAL WATER COMPANY", "EAST VALLEY WATER DISTRICT", "CALISTOGA RANCH", "MOUNT WHITNEY GOLF CLUB", "GUATAY MUTUAL BENEFIT CORPORATION", "HURON, CITY OF"], "Non-Native Violations": [2, 3, 4, 11, 18, 26], "Rank": 3, "Total Rank": 7, "Percentile": 57.14, "Latitude": 37.1363, "Longitude": -118.27335, "PWSID": "90600160", "Embed": ["https://plotly.com/~arnav10g/30.embed", "https://plotly.com/~arnav10g/32.embed", "https://plotly.com/~arnav10g/34.embed", "https://plotly.com/~arnav10g/36.embed"], "Checks": 11.0}, "90605150": {"Native Name": "Susanville Upper Rancheria", "Native Violations": 3, "Non-Native Names": ["PASKENTA COMM. SERVICES DIST.", "THE COURTLAND GROUP", "MT. GEORGE ESTATES", "BOULEVARD PINES MOBILE HOME AND RV PARK"], "Non-Native Violations": [4, 7, 8, 9], "Rank": 5, "Total Rank": 5, "Percentile": 0.0, "Latitude": 40.474951, "Longitude": -120.67685, "PWSID": "90605150", "Embed": ["https://plotly.com/~arnav10g/38.embed", "https://plotly.com/~arnav10g/40.embed", "https://plotly.com/~arnav10g/42.embed", "https://plotly.com/~arnav10g/44.embed"], "Checks": 3.0}, "90605024": {"Native Name": "Sycuan", "Native Violations": 2, "Non-Native Names": ["DOGWOOD BLUE JAY CYN IMP", "SACRAMENTO SIKH SOCIETY", "SUPER DRIVE IN", "VACA VILLA APARTMENTS", "EDNA BEAMAN ELEMENTARY SCHOOL", "LAKE ELEMENTARY SCHOOL", "PESCADERO HIGH SCHOOL", "SACRAMENTO SOFTBALL COMPLEX (SWS)", "NEWELL COUNTY WATER DISTRICT", "APPLE VALLEY VIEW MWC", "BASS LAKE ANNEX 3", "NORTH FORK ELEMENTARY SCHOOL", "TWIN VALLEY INC", "FCSA #34/ MILLERTON NEW TOWN", "MD 24 TEAFORD MEADOW LAKES", "FAMILY TREE FARMS", "BAR-LEN MWC", "MILLSTREAM MOBILE HOME PARK", "LEMOORE, CITY OF", "LIZZE ENTERPRISES", "FINLEYS"], "Non-Native Violations": [1, 1, 1, 1, 2, 2, 2, 2, 3, 6, 9, 11, 11, 12, 13, 17, 19, 24, 25, 27, 30], "Rank": 14, "Total Rank": 22, "Percentile": 36.36, "Latitude": 32.788736, "Longitude": -116.90487, "PWSID": "90605024", "Embed": ["https://plotly.com/~arnav10g/46.embed", "https://plotly.com/~arnav10g/48.embed", "https://plotly.com/~arnav10g/50.embed", "https://plotly.com/~arnav10g/52.embed"], "Checks": 2.0}, "90605124": {"Native Name": "Table Bluff (New) Rancheria", "Native Violations": 0, "Non-Native Names": ["ALPHA OMEGA WINERY", "BIG SUR BAZAAR WS", "LEAPIN' LIZARD RV RANCH", "LOMA VISTA INN WS", "MESA  WATER DISTRICT", "ANCHORPOINT CHRISTIAN SCHOOL", "DEL ORO RIVER ISLAND SERV TERR #2", "BUTTE CITY COMMUNITY S.D.", "OASIS PROPERTY OWNERS ASSOCIATION", "BERRYESSA HIGHLANDS", "EAST OROSI CSD", "CANTUA CREEK VINEYARDS, IV, LLC.", "KNOLL ENTERPRISES"], "Non-Native Violations": [1, 1, 1, 2, 2, 3, 7, 8, 13, 22, 25, 26, 41], "Rank": 14, "Total Rank": 14, "Percentile": 0.0, "Latitude": 40.659753, "Longitude": -124.22153, "PWSID": "90605124", "Embed": ["https://plotly.com/~arnav10g/53.embed", "https://plotly.com/~arnav10g/54.embed", "https://plotly.com/~arnav10g/56.embed", "https://plotly.com/~arnav10g/58.embed"], "Checks": 0.0}, "90600154": {"Native Name": "Table Mountain Rancheria", "Native Violations": 9, "Non-Native Names": ["ALPHA OMEGA WINERY", "BIG SUR BAZAAR WS", "LEAPIN' LIZARD RV RANCH", "LOMA VISTA INN WS", "MESA  WATER DISTRICT", "ANCHORPOINT CHRISTIAN SCHOOL", "DEL ORO RIVER ISLAND SERV TERR #2", "BUTTE CITY COMMUNITY S.D.", "OASIS PROPERTY OWNERS ASSOCIATION", "BERRYESSA HIGHLANDS", "EAST OROSI CSD", "CANTUA CREEK VINEYARDS, IV, LLC.", "KNOLL ENTERPRISES"], "Non-Native Violations": [1, 1, 1, 2, 2, 3, 7, 8, 13, 22, 25, 26, 41], "Rank": 6, "Total Rank": 14, "Percentile": 57.14, "Latitude": 40.789753000000005, "Longitude": -124.24153, "PWSID": "90600154", "Embed": ["https://plotly.com/~arnav10g/60.embed", "https://plotly.com/~arnav10g/62.embed", "https://plotly.com/~arnav10g/64.embed", "https://plotly.com/~arnav10g/66.embed"], "Checks": 9.0}, "90605167": {"Native Name": "Temalpakh Farm", "Native Violations": 0, "Non-Native Names": ["JACUMBA VALLEY RANCH WATER COMPANY", "99 PALMS INN AND SUITES", "LAIRD FAMILY ESTATE", "SAC VALLEY TRUCK STOP", "SHANT BHAVAN PUNJABI FUNERAL HOME", "PLAINVIEW MUTUAL WATER COMPANY", "GOOSELAKE WATER COMPANY", "RANCHO ESTATES MUTUAL WATER CO.", "STOCKTON BAPTIST CHURCH", "WINSHIP ELEMENTARY SCHOOL", "ROUND MOUNTAIN WATER COMPANY", "SIERRA EAST HOA", "OLD SUGAR MILL WINERY"], "Non-Native Violations": [1, 3, 3, 3, 4, 6, 8, 14, 17, 18, 21, 44, 76], "Rank": 14, "Total Rank": 14, "Percentile": 0.0, "Latitude": 33.579872, "Longitude": -116.17656, "PWSID": "90605167", "Embed": ["https://plotly.com/~arnav10g/67.embed", "https://plotly.com/~arnav10g/68.embed", "https://plotly.com/~arnav10g/70.embed", "https://plotly.com/~arnav10g/72.embed"], "Checks": 0.0}, "90605161": {"Native Name": "Thunder Valley Casino", "Native Violations": 2, "Non-Native Names": ["PRESTON WINERY", "ROARING CAMP", "GURNSEY AVENUE MUTUAL WATER SYSTEM", "KERN OIL AND REFINING CO.", "EB STONE", "OASIS GARDENS WATER CO.", "ELM COURT"], "Non-Native Violations": [1, 2, 4, 4, 11, 21, 24], "Rank": 6, "Total Rank": 8, "Percentile": 25.0, "Latitude": 38.902873, "Longitude": -121.26795, "PWSID": "90605161", "Embed": ["https://plotly.com/~arnav10g/74.embed", "https://plotly.com/~arnav10g/76.embed", "https://plotly.com/~arnav10g/78.embed", "https://plotly.com/~arnav10g/80.embed"], "Checks": 2.0}, "90605116": {"Native Name": "Torres-Martinez Avenue 64", "Native Violations": 3, "Non-Native Names": ["JACUMBA VALLEY RANCH WATER COMPANY", "99 PALMS INN AND SUITES", "LAIRD FAMILY ESTATE", "SAC VALLEY TRUCK STOP", "SHANT BHAVAN PUNJABI FUNERAL HOME", "PLAINVIEW MUTUAL WATER COMPANY", "GOOSELAKE WATER COMPANY", "RANCHO ESTATES MUTUAL WATER CO.", "STOCKTON BAPTIST CHURCH", "WINSHIP ELEMENTARY SCHOOL", "ROUND MOUNTAIN WATER COMPANY", "SIERRA EAST HOA", "OLD SUGAR MILL WINERY"], "Non-Native Violations": [1, 3, 3, 3, 4, 6, 8, 14, 17, 18, 21, 44, 76], "Rank": 10, "Total Rank": 14, "Percentile": 28.569999999999993, "Latitude": 33.466287, "Longitude": -116.0688, "PWSID": "90605116", "Embed": ["https://plotly.com/~arnav10g/82.embed", "https://plotly.com/~arnav10g/84.embed", "https://plotly.com/~arnav10g/86.embed", "https://plotly.com/~arnav10g/88.embed"], "Checks": 3.0}, "90605130": {"Native Name": "Torres-Martinez Clinic", "Native Violations": 3, "Non-Native Names": ["JACUMBA VALLEY RANCH WATER COMPANY", "99 PALMS INN AND SUITES", "LAIRD FAMILY ESTATE", "SAC VALLEY TRUCK STOP", "SHANT BHAVAN PUNJABI FUNERAL HOME", "PLAINVIEW MUTUAL WATER COMPANY", "GOOSELAKE WATER COMPANY", "RANCHO ESTATES MUTUAL WATER CO.", "STOCKTON BAPTIST CHURCH", "WINSHIP ELEMENTARY SCHOOL", "ROUND MOUNTAIN WATER COMPANY", "SIERRA EAST HOA", "OLD SUGAR MILL WINERY"], "Non-Native Violations": [1, 3, 3, 3, 4, 6, 8, 14, 17, 18, 21, 44, 76], "Rank": 10, "Total Rank": 14, "Percentile": 28.569999999999993, "Latitude": 33.476287, "Longitude": -116.0688, "PWSID": "90605130", "Embed": ["https://plotly.com/~arnav10g/90.embed", "https://plotly.com/~arnav10g/92.embed", "https://plotly.com/~arnav10g/94.embed", "https://plotly.com/~arnav10g/96.embed"], "Checks": 3.0}, "90605074": {"Native Name": "Tule River Apple Valley", "Native Violations": 5, "Non-Native Names": ["PINE VALLEY BIBLE CONFERENCE CENTER", "ESCALON GOLF COURSE WS", "PIGEON POINT YOUTH HOSTEL", "INTERSTATE TRUCK CENTER VALLEY PETERBILT", "FCSA #30/EL PORVENIR"], "Non-Native Violations": [2, 3, 3, 17, 33], "Rank": 3, "Total Rank": 6, "Percentile": 50.0, "Latitude": 36.085342, "Longitude": -119.5548, "PWSID": "90605074", "Embed": ["https://plotly.com/~arnav10g/98.embed", "https://plotly.com/~arnav10g/100.embed", "https://plotly.com/~arnav10g/102.embed", "https://plotly.com/~arnav10g/104.embed"], "Checks": 5.0}, "90600156": {"Native Name": "Tule River Reservation Main", "Native Violations": 152, "Non-Native Names": ["PINE VALLEY BIBLE CONFERENCE CENTER", "ESCALON GOLF COURSE WS", "PIGEON POINT YOUTH HOSTEL", "INTERSTATE TRUCK CENTER VALLEY PETERBILT", "FCSA #30/EL PORVENIR"], "Non-Native Violations": [2, 3, 3, 17, 33], "Rank": 1, "Total Rank": 6, "Percentile": 83.33, "Latitude": 36.225342, "Longitude": -119.3548, "PWSID": "90600156", "Embed": ["https://plotly.com/~arnav10g/106.embed", "https://plotly.com/~arnav10g/108.embed", "https://plotly.com/~arnav10g/110.embed", "https://plotly.com/~arnav10g/112.embed"], "Checks": 152.0}, "90605149": {"Native Name": "Tuolumne - Black Oak Casino", "Native Violations": 8, "Non-Native Names": ["GURDWARA GUR NANAK PARKASH - FRESNO", "MAMMOTH POOL MOBILE HOME PARK"], "Non-Native Violations": [10, 25], "Rank": 3, "Total Rank": 3, "Percentile": 0.0, "Latitude": 37.995238, "Longitude": -120.3437, "PWSID": "90605149", "Embed": ["https://plotly.com/~arnav10g/114.embed", "https://plotly.com/~arnav10g/116.embed", "https://plotly.com/~arnav10g/118.embed", "https://plotly.com/~arnav10g/120.embed"], "Checks": 8.0}, "90605169": {"Native Name": "Tuolumne Me-Wuk Ridgeline", "Native Violations": 1, "Non-Native Names": ["GURDWARA GUR NANAK PARKASH - FRESNO", "MAMMOTH POOL MOBILE HOME PARK"], "Non-Native Violations": [10, 25], "Rank": 3, "Total Rank": 3, "Percentile": 0.0, "Latitude": 38.005238, "Longitude": -120.3437, "PWSID": "90605169", "Embed": ["https://plotly.com/~arnav10g/122.embed", "https://plotly.com/~arnav10g/124.embed", "https://plotly.com/~arnav10g/126.embed", "https://plotly.com/~arnav10g/128.embed"], "Checks": 1.0}, "90605122": {"Native Name": "Turner Trailer Park", "Native Violations": 12, "Non-Native Names": ["DOGWOOD BLUE JAY CYN IMP", "SACRAMENTO SIKH SOCIETY", "SUPER DRIVE IN", "VACA VILLA APARTMENTS", "EDNA BEAMAN ELEMENTARY SCHOOL", "LAKE ELEMENTARY SCHOOL", "PESCADERO HIGH SCHOOL", "SACRAMENTO SOFTBALL COMPLEX (SWS)", "NEWELL COUNTY WATER DISTRICT", "APPLE VALLEY VIEW MWC", "BASS LAKE ANNEX 3", "NORTH FORK ELEMENTARY SCHOOL", "TWIN VALLEY INC", "FCSA #34/ MILLERTON NEW TOWN", "MD 24 TEAFORD MEADOW LAKES", "FAMILY TREE FARMS", "BAR-LEN MWC", "MILLSTREAM MOBILE HOME PARK", "LEMOORE, CITY OF", "LIZZE ENTERPRISES", "FINLEYS"], "Non-Native Violations": [1, 1, 1, 1, 2, 2, 2, 2, 3, 6, 9, 11, 11, 12, 13, 17, 19, 24, 25, 27, 30], "Rank": 8, "Total Rank": 22, "Percentile": 63.64, "Latitude": 33.261748, "Longitude": -117.04027, "PWSID": "90605122", "Embed": ["https://plotly.com/~arnav10g/130.embed", "https://plotly.com/~arnav10g/132.embed", "https://plotly.com/~arnav10g/134.embed", "https://plotly.com/~arnav10g/136.embed"], "Checks": 12.0}, "90605025": {"Native Name": "Upper Lake Hardisty System", "Native Violations": 0, "Non-Native Names": ["CAL FIRE - ISHI CONSERVATION CAMP", "7042 FOLSOM LLC WATER SYSTEM", "DIAMOND JACK'S RV RANCH", "SILVERFORK WATER ASSOCIATION", "ELKHORN REGIONAL PARK", "MATTOLE ELEMENTARY SCHOOL", "MELA'S MEXICAN RESTAURANT", "FANTESCA WINERY", "WINDY HILL WINERY", "YOSEMITE FORKS EST MUTUAL", "RIO BRAVO GREELEY SCHOOL WATER SYSTEM", "ALLENSWORTH CSD", "DUNNIGAN CHEVRON", "SHADY OAKS TRAILER RANCH", "ALPAUGH COMMUNITY SERVICES DISTRICT", "BARRY ELEMENTARY SCHOOL", "SAINT ANTHONY TRAILER PARK", "PANOCHE WATER DISTRICT"], "Non-Native Violations": [1, 2, 2, 2, 3, 3, 3, 6, 9, 9, 11, 12, 13, 14, 18, 20, 20, 22], "Rank": 19, "Total Rank": 19, "Percentile": 0.0, "Latitude": 39.172397, "Longitude": -122.50474, "PWSID": "90605025", "Embed": ["https://plotly.com/~arnav10g/137.embed", "https://plotly.com/~arnav10g/138.embed", "https://plotly.com/~arnav10g/140.embed", "https://plotly.com/~arnav10g/142.embed"], "Checks": 0.0}, "90600158": {"Native Name": "Viejas Community System", "Native Violations": 0, "Non-Native Names": ["EDDO'S HARBOR & R V PARK", "NATIONAL CEMENT CO.-LEBEC PLANT", "FLORISTON WATER SYSTEM", "TRACT 92  CSD", "CEMEX - ALABAMA", "THE VILLAGE MOBILE HOME PARK"], "Non-Native Violations": [1, 3, 5, 5, 13, 15], "Rank": 7, "Total Rank": 7, "Percentile": 0.0, "Latitude": 32.823102, "Longitude": -116.73864, "PWSID": "90600158", "Embed": ["https://plotly.com/~arnav10g/143.embed", "https://plotly.com/~arnav10g/144.embed", "https://plotly.com/~arnav10g/146.embed", "https://plotly.com/~arnav10g/148.embed"], "Checks": 0.0}, "90600236": {"Native Name": "Villa Shores", "Native Violations": 3, "Non-Native Names": ["JACUMBA VALLEY RANCH WATER COMPANY", "99 PALMS INN AND SUITES", "LAIRD FAMILY ESTATE", "SAC VALLEY TRUCK STOP", "SHANT BHAVAN PUNJABI FUNERAL HOME", "PLAINVIEW MUTUAL WATER COMPANY", "GOOSELAKE WATER COMPANY", "RANCHO ESTATES MUTUAL WATER CO.", "STOCKTON BAPTIST CHURCH", "WINSHIP ELEMENTARY SCHOOL", "ROUND MOUNTAIN WATER COMPANY", "SIERRA EAST HOA", "OLD SUGAR MILL WINERY"], "Non-Native Violations": [1, 3, 3, 3, 4, 6, 8, 14, 17, 18, 21, 44, 76], "Rank": 10, "Total Rank": 14, "Percentile": 28.569999999999993, "Latitude": 33.528333, "Longitude": -114.69905, "PWSID": "90600236", "Embed": ["https://plotly.com/~arnav10g/150.embed", "https://plotly.com/~arnav10g/152.embed", "https://plotly.com/~arnav10g/154.embed", "https://plotly.com/~arnav10g/156.embed"], "Checks": 3.0}, "90600362": {"Native Name": "Washoe Tribe Woodfords", "Native Violations": 3, "Non-Native Names": ["PASKENTA COMM. SERVICES DIST.", "THE COURTLAND GROUP", "MT. GEORGE ESTATES", "BOULEVARD PINES MOBILE HOME AND RV PARK"], "Non-Native Violations": [4, 7, 8, 9], "Rank": 5, "Total Rank": 5, "Percentile": 0.0, "Latitude": 38.76467, "Longitude": -119.85236, "PWSID": "90600362", "Embed": ["https://plotly.com/~arnav10g/158.embed", "https://plotly.com/~arnav10g/160.embed", "https://plotly.com/~arnav10g/162.embed", "https://plotly.com/~arnav10g/164.embed"], "Checks": 3.0}, "90600132": {"Native Name": "Water Wheel Resort", "Native Violations": 1, "Non-Native Names": ["JACUMBA VALLEY RANCH WATER COMPANY", "99 PALMS INN AND SUITES", "LAIRD FAMILY ESTATE", "SAC VALLEY TRUCK STOP", "SHANT BHAVAN PUNJABI FUNERAL HOME", "PLAINVIEW MUTUAL WATER COMPANY", "GOOSELAKE WATER COMPANY", "RANCHO ESTATES MUTUAL WATER CO.", "STOCKTON BAPTIST CHURCH", "WINSHIP ELEMENTARY SCHOOL", "ROUND MOUNTAIN WATER COMPANY", "SIERRA EAST HOA", "OLD SUGAR MILL WINERY"], "Non-Native Violations": [1, 3, 3, 3, 4, 6, 8, 14, 17, 18, 21, 44, 76], "Rank": 13, "Total Rank": 14, "Percentile": 7.140000000000001, "Latitude": 33.538333, "Longitude": -114.61905, "PWSID": "90600132", "Embed": ["https://plotly.com/~arnav10g/166.embed", "https://plotly.com/~arnav10g/168.embed", "https://plotly.com/~arnav10g/170.embed", "https://plotly.com/~arnav10g/172.embed"], "Checks": 1.0}, "90600131": {"Native Name": "Wheel-er In Family", "Native Violations": 59, "Non-Native Names": ["JACUMBA VALLEY RANCH WATER COMPANY", "99 PALMS INN AND SUITES", "LAIRD FAMILY ESTATE", "SAC VALLEY TRUCK STOP", "SHANT BHAVAN PUNJABI FUNERAL HOME", "PLAINVIEW MUTUAL WATER COMPANY", "GOOSELAKE WATER COMPANY", "RANCHO ESTATES MUTUAL WATER CO.", "STOCKTON BAPTIST CHURCH", "WINSHIP ELEMENTARY SCHOOL", "ROUND MOUNTAIN WATER COMPANY", "SIERRA EAST HOA", "OLD SUGAR MILL WINERY"], "Non-Native Violations": [1, 3, 3, 3, 4, 6, 8, 14, 17, 18, 21, 44, 76], "Rank": 2, "Total Rank": 14, "Percentile": 85.71000000000001, "Latitude": 34.137179, "Longitude": -114.35823, "PWSID": "90600131", "Embed": ["https://plotly.com/~arnav10g/174.embed", "https://plotly.com/~arnav10g/176.embed", "https://plotly.com/~arnav10g/178.embed", "https://plotly.com/~arnav10g/180.embed"], "Checks": 59.0}, "90605155": {"Native Name": "Yocha Dehe Community Area", "Native Violations": 0, "Non-Native Names": ["PRESTON WINERY", "ROARING CAMP", "GURNSEY AVENUE MUTUAL WATER SYSTEM", "KERN OIL AND REFINING CO.", "EB STONE", "OASIS GARDENS WATER CO.", "ELM COURT"], "Non-Native Violations": [1, 2, 4, 4, 11, 21, 24], "Rank": 8, "Total Rank": 8, "Percentile": 0.0, "Latitude": 38.857328, "Longitude": -122.24486, "PWSID": "90605155", "Embed": ["https://plotly.com/~arnav10g/181.embed", "https://plotly.com/~arnav10g/182.embed", "https://plotly.com/~arnav10g/184.embed", "https://plotly.com/~arnav10g/186.embed"], "Checks": 0.0}, "90605033": {"Native Name": "Yurok - Kepel", "Native Violations": 28, "Non-Native Names": ["ALPHA OMEGA WINERY", "BIG SUR BAZAAR WS", "LEAPIN' LIZARD RV RANCH", "LOMA VISTA INN WS", "MESA  WATER DISTRICT", "ANCHORPOINT CHRISTIAN SCHOOL", "DEL ORO RIVER ISLAND SERV TERR #2", "BUTTE CITY COMMUNITY S.D.", "OASIS PROPERTY OWNERS ASSOCIATION", "BERRYESSA HIGHLANDS", "EAST OROSI CSD", "CANTUA CREEK VINEYARDS, IV, LLC.", "KNOLL ENTERPRISES"], "Non-Native Violations": [1, 1, 1, 2, 2, 3, 7, 8, 13, 22, 25, 26, 41], "Rank": 2, "Total Rank": 14, "Percentile": 85.71000000000001, "Latitude": 41.59823, "Longitude": -124.02075, "PWSID": "90605033", "Embed": ["https://plotly.com/~amotiani19/9.embed", "https://plotly.com/~amotiani19/7.embed", "https://plotly.com/~amotiani19/12.embed", "https://plotly.com/~amotiani19/14.embed"], "Checks": 28.0}, "90600161": {"Native Name": "Yurok - McCoy - Kenek", "Native Violations": 80, "Non-Native Names": ["ALPHA OMEGA WINERY", "BIG SUR BAZAAR WS", "LEAPIN' LIZARD RV RANCH", "LOMA VISTA INN WS", "MESA  WATER DISTRICT", "ANCHORPOINT CHRISTIAN SCHOOL", "DEL ORO RIVER ISLAND SERV TERR #2", "BUTTE CITY COMMUNITY S.D.", "OASIS PROPERTY OWNERS ASSOCIATION", "BERRYESSA HIGHLANDS", "EAST OROSI CSD", "CANTUA CREEK VINEYARDS, IV, LLC.", "KNOLL ENTERPRISES"], "Non-Native Violations": [1, 1, 1, 2, 2, 3, 7, 8, 13, 22, 25, 26, 41], "Rank": 1, "Total Rank": 14, "Percentile": 92.86, "Latitude": 41.52823, "Longitude": -124.03075, "PWSID": "90600161", "Embed": ["https://plotly.com/~amotiani19/16.embed", "https://plotly.com/~amotiani19/18.embed", "https://plotly.com/~amotiani19/20.embed", "https://plotly.com/~amotiani19/22.embed"], "Checks": 80.0}, "90605014": {"Native Name": "Yurok - Requa", "Native Violations": 7, "Non-Native Names": ["ALPHA OMEGA WINERY", "BIG SUR BAZAAR WS", "LEAPIN' LIZARD RV RANCH", "LOMA VISTA INN WS", "MESA  WATER DISTRICT", "ANCHORPOINT CHRISTIAN SCHOOL", "DEL ORO RIVER ISLAND SERV TERR #2", "BUTTE CITY COMMUNITY S.D.", "OASIS PROPERTY OWNERS ASSOCIATION", "BERRYESSA HIGHLANDS", "EAST OROSI CSD", "CANTUA CREEK VINEYARDS, IV, LLC.", "KNOLL ENTERPRISES"], "Non-Native Violations": [1, 1, 1, 2, 2, 3, 7, 8, 13, 22, 25, 26, 41], "Rank": 7, "Total Rank": 14, "Percentile": 50.0, "Latitude": 41.40823, "Longitude": -124.00075, "PWSID": "90605014", "Embed": ["https://plotly.com/~amotiani19/24.embed", "https://plotly.com/~amotiani19/26.embed", "https://plotly.com/~amotiani19/28.embed", "https://plotly.com/~amotiani19/30.embed"], "Checks": 7.0}, "90605143": {"Native Name": "Yurok - Terwer Water System", "Native Violations": 57, "Non-Native Names": ["ALPHA OMEGA WINERY", "BIG SUR BAZAAR WS", "LEAPIN' LIZARD RV RANCH", "LOMA VISTA INN WS", "MESA  WATER DISTRICT", "ANCHORPOINT CHRISTIAN SCHOOL", "DEL ORO RIVER ISLAND SERV TERR #2", "BUTTE CITY COMMUNITY S.D.", "OASIS PROPERTY OWNERS ASSOCIATION", "BERRYESSA HIGHLANDS", "EAST OROSI CSD", "CANTUA CREEK VINEYARDS, IV, LLC.", "KNOLL ENTERPRISES"], "Non-Native Violations": [1, 1, 1, 2, 2, 3, 7, 8, 13, 22, 25, 26, 41], "Rank": 1, "Total Rank": 14, "Percentile": 92.86, "Latitude": 41.34823, "Longitude": -123.997075, "PWSID": "90605143", "Embed": ["https://plotly.com/~amotiani19/32.embed", "https://plotly.com/~amotiani19/34.embed", "https://plotly.com/~amotiani19/36.embed", "https://plotly.com/~amotiani19/38.embed"], "Checks": 57.0}, "90600134": {"Native Name": "Yurok - Wautec", "Native Violations": 19, "Non-Native Names": ["ALPHA OMEGA WINERY", "BIG SUR BAZAAR WS", "LEAPIN' LIZARD RV RANCH", "LOMA VISTA INN WS", "MESA  WATER DISTRICT", "ANCHORPOINT CHRISTIAN SCHOOL", "DEL ORO RIVER ISLAND SERV TERR #2", "BUTTE CITY COMMUNITY S.D.", "OASIS PROPERTY OWNERS ASSOCIATION", "BERRYESSA HIGHLANDS", "EAST OROSI CSD", "CANTUA CREEK VINEYARDS, IV, LLC.", "KNOLL ENTERPRISES"], "Non-Native Violations": [1, 1, 1, 2, 2, 3, 7, 8, 13, 22, 25, 26, 41], "Rank": 5, "Total Rank": 14, "Percentile": 64.28999999999999, "Latitude": 41.44823, "Longitude": -124.02075, "PWSID": "90600134", "Embed": ["https://plotly.com/~amotiani19/40.embed", "https://plotly.com/~amotiani19/42.embed", "https://plotly.com/~amotiani19/44.embed", "https://plotly.com/~amotiani19/46.embed"], "Checks": 19.0}, "90605006": {"Native Name": "Yurok - Weitchpec", "Native Violations": 19, "Non-Native Names": ["ALPHA OMEGA WINERY", "BIG SUR BAZAAR WS", "LEAPIN' LIZARD RV RANCH", "LOMA VISTA INN WS", "MESA  WATER DISTRICT", "ANCHORPOINT CHRISTIAN SCHOOL", "DEL ORO RIVER ISLAND SERV TERR #2", "BUTTE CITY COMMUNITY S.D.", "OASIS PROPERTY OWNERS ASSOCIATION", "BERRYESSA HIGHLANDS", "EAST OROSI CSD", "CANTUA CREEK VINEYARDS, IV, LLC.", "KNOLL ENTERPRISES"], "Non-Native Violations": [1, 1, 1, 2, 2, 3, 7, 8, 13, 22, 25, 26, 41], "Rank": 5, "Total Rank": 14, "Percentile": 64.28999999999999, "Latitude": 41.398230000000005, "Longitude": -124.05075, "PWSID": "90605006", "Embed": ["https://plotly.com/~amotiani19/48.embed", "https://plotly.com/~amotiani19/50.embed", "https://plotly.com/~amotiani19/52.embed", "https://plotly.com/~amotiani19/54.embed"], "Checks": 19.0}}